{"assets":{"99B4D0FF28E2692CD0C57104DAC27CED":{"type":"texture","index":13,"assetRequest":{"type":"slide","state":"contents","slide":"none"},"url":{"native":"assets\/55017EE4-CCBB-4D9C-81A7-850B66627E51.pdf"},"width":425,"height":179},"D1BCC90F4A817BAEF10B4EC9B04D169D":{"type":"texture","index":7,"assetRequest":{"type":"slide","state":"contents","slide":"none"},"url":{"native":"assets\/55017EE4-CCBB-4D9C-81A7-850B66627E51.pdf"},"width":205,"height":97},"D6ACCEF746E29E97D128626FF2816D0F":{"type":"texture","index":1,"assetRequest":{"type":"slide","state":"contents","slide":"none"},"url":{"native":"assets\/55017EE4-CCBB-4D9C-81A7-850B66627E51.pdf"},"width":352,"height":39},"7F9169F746AA870A0DEF2212163E8B53":{"type":"texture","index":17,"assetRequest":{"type":"slide","state":"contents","slide":"none"},"url":{"native":"assets\/55017EE4-CCBB-4D9C-81A7-850B66627E51.pdf"},"width":984,"height":137},"3B4F8D6EE81A914129782883B58270E9":{"type":"texture","index":2,"assetRequest":{"type":"slide","state":"contents","slide":"none"},"url":{"native":"assets\/55017EE4-CCBB-4D9C-81A7-850B66627E51.pdf"},"width":248,"height":51},"0E8FEB164291BE6990A485D710DD11FA":{"type":"texture","index":3,"assetRequest":{"type":"slide","state":"contents","slide":"none"},"url":{"native":"assets\/55017EE4-CCBB-4D9C-81A7-850B66627E51.pdf"},"width":205,"height":97},"2E7045BD920F3487C77D8EABFECE1D2D":{"type":"texture","index":5,"assetRequest":{"type":"slide","state":"contents","slide":"none"},"url":{"native":"assets\/55017EE4-CCBB-4D9C-81A7-850B66627E51.pdf"},"width":205,"height":96},"8D8076FC571C884B99B78997664A31AB":{"type":"texture","index":10,"assetRequest":{"type":"slide","state":"contents","slide":"none"},"url":{"native":"assets\/55017EE4-CCBB-4D9C-81A7-850B66627E51.pdf"},"width":528,"height":238},"DE7E69848A2A2C788BBBE86BB17CBA75":{"type":"texture","index":21,"assetRequest":{"type":"slide","state":"contents","slide":"none"},"url":{"native":"assets\/55017EE4-CCBB-4D9C-81A7-850B66627E51.pdf"},"width":356,"height":26},"4A112B40B3884597F33BB6F30BFED3E9":{"type":"texture","index":8,"assetRequest":{"type":"slide","state":"contents","slide":"none"},"url":{"native":"assets\/55017EE4-CCBB-4D9C-81A7-850B66627E51.pdf"},"width":387,"height":269},"B9AA89F1E301910A2B675E6B21148B58":{"type":"texture","index":14,"assetRequest":{"type":"slide","state":"contents","slide":"none"},"url":{"native":"assets\/55017EE4-CCBB-4D9C-81A7-850B66627E51.pdf"},"width":528,"height":238},"2833E5D319081570F97B4EAA52A46BB0":{"type":"texture","index":0,"assetRequest":{"type":"slide","state":"contents","slide":"none"},"url":{"native":"assets\/55017EE4-CCBB-4D9C-81A7-850B66627E51.pdf"},"width":1920,"height":1080},"92F080D6EFD25320C74C7DA152EDEF71":{"type":"texture","index":15,"assetRequest":{"type":"slide","state":"contents","slide":"none"},"url":{"native":"assets\/55017EE4-CCBB-4D9C-81A7-850B66627E51.pdf"},"width":869,"height":564},"1796028C98209D0165F52AB38FB587DF":{"type":"texture","index":11,"assetRequest":{"type":"slide","state":"contents","slide":"none"},"url":{"native":"assets\/55017EE4-CCBB-4D9C-81A7-850B66627E51.pdf"},"width":624,"height":197},"C01262779C34742FCAB4F9FA6FF78572":{"type":"texture","index":18,"assetRequest":{"type":"slide","state":"contents","slide":"none"},"url":{"native":"assets\/55017EE4-CCBB-4D9C-81A7-850B66627E51.pdf"},"width":305,"height":49},"78B2571B4C942879C0A8C8D665EEA93B":{"type":"texture","index":16,"assetRequest":{"type":"slide","state":"contents","slide":"none"},"url":{"native":"assets\/55017EE4-CCBB-4D9C-81A7-850B66627E51.pdf"},"width":869,"height":558},"EDE3317141A20CA829F956C46062911A":{"type":"texture","index":20,"assetRequest":{"type":"slide","state":"contents","slide":"none"},"url":{"native":"assets\/55017EE4-CCBB-4D9C-81A7-850B66627E51.pdf"},"width":371,"height":51},"A8DB8D9536F81A2527E0B05BA8FCC94D":{"type":"texture","index":6,"assetRequest":{"type":"slide","state":"contents","slide":"none"},"url":{"native":"assets\/55017EE4-CCBB-4D9C-81A7-850B66627E51.pdf"},"width":387,"height":322},"9A6D3BC21262E5851D204FFA9173D32E":{"type":"texture","index":19,"assetRequest":{"type":"slide","state":"contents","slide":"none"},"url":{"native":"assets\/55017EE4-CCBB-4D9C-81A7-850B66627E51.pdf"},"width":290,"height":26},"7D0D6ADCFF5A1DA84875F396A1F3D49A":{"type":"texture","index":4,"assetRequest":{"type":"slide","state":"contents","slide":"none"},"url":{"native":"assets\/55017EE4-CCBB-4D9C-81A7-850B66627E51.pdf"},"width":387,"height":190},"C6B68B8849F70C492EB2F1F2F2E8219F":{"type":"texture","index":23,"assetRequest":{"type":"slide","state":"contents","slide":"none"},"url":{"native":"assets\/55017EE4-CCBB-4D9C-81A7-850B66627E51.pdf"},"width":684,"height":315},"87C15DFF8EDFD93167001BD43D51C037":{"type":"texture","index":9,"assetRequest":{"type":"slide","state":"contents","slide":"none"},"url":{"native":"assets\/55017EE4-CCBB-4D9C-81A7-850B66627E51.pdf"},"width":528,"height":305},"6B879764B608788B7470C03483FC0DD4":{"type":"texture","index":22,"assetRequest":{"type":"slide","state":"contents","slide":"none"},"url":{"native":"assets\/55017EE4-CCBB-4D9C-81A7-850B66627E51.pdf"},"width":205,"height":97},"E3ADDBBFD8171082E38ADE95F01AB209":{"type":"texture","index":12,"assetRequest":{"type":"slide","state":"contents","slide":"none"},"url":{"native":"assets\/55017EE4-CCBB-4D9C-81A7-850B66627E51.pdf"},"width":624,"height":269}},"events":[{"effects":[{"beginTime":0,"baseLayer":{"animations":[],"initialState":{"affineTransform":[1,0,0,1,0,0],"masksToBounds":false,"rotation":0,"scale":1,"position":{"pointX":960,"pointY":540},"width":1920,"sublayerTransform":[1,0,0,0,0,1,0,0,0,0,1,0,0,0,0,1],"contentsRect":{"y":0,"x":0,"width":1,"height":1},"opacity":1,"edgeAntialiasingMask":251658240,"height":1080,"hidden":false,"anchorPoint":{"pointX":0.5,"pointY":0.5}},"objectID":"0","layers":[{"animations":[],"initialState":{"affineTransform":[1,0,0,1,0,0],"masksToBounds":false,"rotation":0,"scale":1,"position":{"pointX":960,"pointY":540},"width":1920,"sublayerTransform":[1,0,0,0,0,1,0,0,0,0,1,-0.00035007912466775983,0,0,0,1],"contentsRect":{"y":0,"x":0,"width":1,"height":1},"opacity":1,"edgeAntialiasingMask":251658240,"height":1080,"hidden":false,"anchorPoint":{"pointX":0.5,"pointY":0.5}},"layers":[{"animations":[{"additive":false,"timeOffset":0,"beginTime":0,"repeatCount":0,"fillMode":"both","duration":0.5,"autoreverses":false,"animations":[{"repeatCount":0,"removedOnCompletion":true,"from":{"scalar":0},"timingFunction":"EaseInEaseOut","additive":false,"timeOffset":0,"autoreverses":false,"property":"zPosition","fillMode":"both","duration":0.5,"beginTime":0,"to":{"scalar":0}}],"removedOnCompletion":false}],"initialState":{"affineTransform":[1,0,0,1,0,0],"masksToBounds":false,"rotation":0,"scale":1,"position":{"pointX":960,"pointY":540},"width":1920,"sublayerTransform":[1,0,0,0,0,1,0,0,0,0,1,0,0,0,0,1],"contentsRect":{"y":0,"x":0,"width":1,"height":1},"opacity":1,"edgeAntialiasingMask":251658240,"height":1080,"hidden":false,"anchorPoint":{"pointX":0.5,"pointY":0.5}},"layers":[{"animations":[],"layers":[],"texturedRectangle":{"isBackgroundTexture":true,"singleTextureOpacity":1,"textureType":1,"textBaseline":0,"textXHeight":0,"isVerticalText":false},"initialState":{"affineTransform":[1,0,0,1,0,0],"masksToBounds":false,"rotation":0,"scale":1,"position":{"pointX":960,"pointY":540},"width":1920,"sublayerTransform":[1,0,0,0,0,1,0,0,0,0,1,0,0,0,0,1],"contentsRect":{"y":0,"x":0,"width":1,"height":1},"opacity":1,"edgeAntialiasingMask":0,"height":1080,"hidden":false,"anchorPoint":{"pointX":0.5,"pointY":0.5}},"texture":"2833E5D319081570F97B4EAA52A46BB0"}]}]},{"animations":[{"additive":false,"timeOffset":0,"beginTime":0,"repeatCount":0,"fillMode":"both","duration":0.5,"autoreverses":false,"animations":[{"repeatCount":0,"removedOnCompletion":true,"from":{"scalar":0.001},"timingFunction":"EaseInEaseOut","additive":false,"timeOffset":0,"autoreverses":false,"property":"zPosition","fillMode":"both","duration":0.5,"beginTime":0,"to":{"scalar":0.001}}],"removedOnCompletion":false}],"initialState":{"affineTransform":[1,0,0,1,0,0],"masksToBounds":false,"rotation":0,"scale":1,"position":{"pointX":960.00000000000023,"pointY":117.89044952392581},"width":1728,"sublayerTransform":[1,0,0,0,0,1,0,0,0,0,1,0,0,0,0,1],"contentsRect":{"y":0,"x":0,"width":1,"height":1},"opacity":1,"edgeAntialiasingMask":251658240,"height":138.96035766601562,"hidden":false,"anchorPoint":{"pointX":0.5,"pointY":0.5}},"layers":[{"animations":[{"additive":false,"timeOffset":0,"beginTime":0,"repeatCount":0,"fillMode":"both","duration":0.5,"autoreverses":false,"animations":[{"repeatCount":0,"removedOnCompletion":true,"from":{"scalar":1},"timingFunction":"EaseInEaseOut","additive":false,"timeOffset":0,"autoreverses":false,"property":"transform.scale.x","fillMode":"both","duration":0.5,"beginTime":0,"to":{"scalar":0.99715909090909094}},{"repeatCount":0,"removedOnCompletion":true,"from":{"scalar":1},"timingFunction":"EaseInEaseOut","additive":false,"timeOffset":0,"autoreverses":false,"property":"transform.scale.y","fillMode":"both","duration":0.5,"beginTime":0,"to":{"scalar":1}},{"repeatCount":0,"removedOnCompletion":true,"from":{"texture":"D6ACCEF746E29E97D128626FF2816D0F"},"timingFunction":"EaseInEaseOut","additive":false,"timeOffset":0,"autoreverses":false,"property":"contents","fillMode":"both","duration":0.5,"beginTime":0,"to":{"texture":"D6ACCEF746E29E97D128626FF2816D0F"}},{"repeatCount":0,"removedOnCompletion":true,"from":{"pointX":0,"pointY":0},"timingFunction":"EaseInEaseOut","additive":false,"timeOffset":0,"autoreverses":false,"property":"transform.translation","fillMode":"both","duration":0.5,"beginTime":0,"to":{"pointX":-0.49715909090912191,"pointY":0}}],"removedOnCompletion":false}],"layers":[],"texturedRectangle":{"singleTextureOpacity":1,"textXHeight":0.56923076923076932,"textBaseline":0.94000930969531793,"isBackgroundTexture":true,"isVerticalText":false,"textColor":[0.39215686917304993,0.78431373834609985,0,1],"textureType":6},"initialState":{"affineTransform":[1,0,0,1,0,0],"masksToBounds":false,"rotation":0,"scale":1,"position":{"pointX":864,"pointY":69.480178833007812},"width":352,"sublayerTransform":[1,0,0,0,0,1,0,0,0,0,1,0,0,0,0,1],"contentsRect":{"y":0,"x":0,"width":1,"height":1},"opacity":1,"edgeAntialiasingMask":0,"height":39,"hidden":false,"anchorPoint":{"pointX":0.49715909090909155,"pointY":-0.28486026861728692}},"texture":"D6ACCEF746E29E97D128626FF2816D0F"}]},{"animations":[{"additive":false,"timeOffset":0,"beginTime":0,"repeatCount":0,"fillMode":"both","duration":0.5,"autoreverses":false,"animations":[{"repeatCount":0,"removedOnCompletion":true,"from":{"scalar":0.002},"timingFunction":"EaseInEaseOut","additive":false,"timeOffset":0,"autoreverses":false,"property":"zPosition","fillMode":"both","duration":0.5,"beginTime":0,"to":{"scalar":0.002}}],"removedOnCompletion":false}],"initialState":{"affineTransform":[1,0,0,1,0,0],"masksToBounds":false,"rotation":0,"scale":1,"position":{"pointX":960.00000000000023,"pointY":117.89044952392581},"width":1728,"sublayerTransform":[1,0,0,0,0,1,0,0,0,0,1,0,0,0,0,1],"contentsRect":{"y":0,"x":0,"width":1,"height":1},"opacity":1,"edgeAntialiasingMask":251658240,"height":138.96035766601562,"hidden":false,"anchorPoint":{"pointX":0.5,"pointY":0.5}},"layers":[{"animations":[{"additive":false,"timeOffset":0,"beginTime":0,"repeatCount":0,"fillMode":"both","duration":0.5,"autoreverses":false,"animations":[{"repeatCount":0,"removedOnCompletion":true,"from":{"scalar":1},"timingFunction":"EaseInEaseOut","additive":false,"timeOffset":0,"autoreverses":false,"property":"transform.scale.x","fillMode":"both","duration":0.5,"beginTime":0,"to":{"scalar":0.99596774193548387}},{"repeatCount":0,"removedOnCompletion":true,"from":{"scalar":1},"timingFunction":"EaseInEaseOut","additive":false,"timeOffset":0,"autoreverses":false,"property":"transform.scale.y","fillMode":"both","duration":0.5,"beginTime":0,"to":{"scalar":1}},{"repeatCount":0,"removedOnCompletion":true,"from":{"texture":"3B4F8D6EE81A914129782883B58270E9"},"timingFunction":"EaseInEaseOut","additive":false,"timeOffset":0,"autoreverses":false,"property":"contents","fillMode":"both","duration":0.5,"beginTime":0,"to":{"texture":"3B4F8D6EE81A914129782883B58270E9"}},{"repeatCount":0,"removedOnCompletion":true,"from":{"pointX":0,"pointY":0},"timingFunction":"EaseInEaseOut","additive":false,"timeOffset":0,"autoreverses":false,"property":"transform.translation","fillMode":"both","duration":0.5,"beginTime":0,"to":{"pointX":-0.5,"pointY":0}}],"removedOnCompletion":false}],"layers":[],"texturedRectangle":{"singleTextureOpacity":1,"textXHeight":0.58823529411764708,"textBaseline":0.85118110273398662,"isBackgroundTexture":true,"isVerticalText":false,"textColor":[0.39215686917304993,0.78431373834609985,0,1],"textureType":6},"initialState":{"affineTransform":[1,0,0,1,0,0],"masksToBounds":false,"rotation":0,"scale":1,"position":{"pointX":864,"pointY":69.480178833007812},"width":248,"sublayerTransform":[1,0,0,0,0,1,0,0,0,0,1,0,0,0,0,1],"contentsRect":{"y":0,"x":0,"width":1,"height":1},"opacity":1,"edgeAntialiasingMask":0,"height":51,"hidden":false,"anchorPoint":{"pointX":0.50000000000000089,"pointY":1.0958911671358003}},"texture":"3B4F8D6EE81A914129782883B58270E9"}]},{"animations":[{"additive":false,"timeOffset":0,"beginTime":0,"repeatCount":0,"fillMode":"both","duration":0.5,"autoreverses":false,"animations":[{"repeatCount":0,"removedOnCompletion":true,"from":{"scalar":0.0030000000000000001},"timingFunction":"EaseInEaseOut","additive":false,"timeOffset":0,"autoreverses":false,"property":"zPosition","fillMode":"both","duration":0.5,"beginTime":0,"to":{"scalar":0.0030000000000000001}}],"removedOnCompletion":false}],"initialState":{"affineTransform":[1,0,0,1,0,0],"masksToBounds":false,"rotation":0,"scale":1,"position":{"pointX":199.78756504968891,"pointY":271.34736690639716},"width":250,"sublayerTransform":[1,0,0,0,0,1,0,0,0,0,1,0,0,0,0,1],"contentsRect":{"y":0,"x":0,"width":1,"height":1},"opacity":1,"edgeAntialiasingMask":251658240,"height":91.757492065429688,"hidden":false,"anchorPoint":{"pointX":0.5,"pointY":0.5}},"layers":[{"animations":[{"additive":false,"timeOffset":0,"beginTime":0,"repeatCount":0,"fillMode":"both","duration":0.5,"autoreverses":false,"animations":[{"repeatCount":0,"removedOnCompletion":true,"from":{"scalar":1},"timingFunction":"EaseInEaseOut","additive":false,"timeOffset":0,"autoreverses":false,"property":"opacity","fillMode":"forwards","duration":0.16664999999999999,"beginTime":0,"to":{"scalar":0}},{"additive":false,"timeOffset":0,"beginTime":0.16664999999999999,"from":{"scalar":true},"repeatCount":0,"fillMode":"forwards","duration":0.33335000000000004,"autoreverses":false,"property":"hidden","to":{"scalar":true},"removedOnCompletion":true}],"removedOnCompletion":false}],"layers":[],"texturedRectangle":{"isBackgroundTexture":true,"singleTextureOpacity":1,"textureType":5,"textBaseline":0,"textXHeight":0,"isVerticalText":false},"initialState":{"affineTransform":[1,0,0,1,0,0],"masksToBounds":false,"rotation":0,"scale":1,"position":{"pointX":100,"pointY":45.878746032714844},"width":205,"sublayerTransform":[1,0,0,0,0,1,0,0,0,0,1,0,0,0,0,1],"contentsRect":{"y":0,"x":0,"width":1,"height":1},"opacity":1,"edgeAntialiasingMask":0,"height":97,"hidden":false,"anchorPoint":{"pointX":0.50140275633994591,"pointY":0.498426462952548}},"texture":"0E8FEB164291BE6990A485D710DD11FA"}]},{"animations":[{"additive":false,"timeOffset":0,"beginTime":0,"repeatCount":0,"fillMode":"both","duration":0.5,"autoreverses":false,"animations":[{"repeatCount":0,"removedOnCompletion":true,"from":{"scalar":0.0040000000000000001},"timingFunction":"EaseInEaseOut","additive":false,"timeOffset":0,"autoreverses":false,"property":"zPosition","fillMode":"both","duration":0.5,"beginTime":0,"to":{"scalar":0.0040000000000000001}}],"removedOnCompletion":false}],"initialState":{"affineTransform":[1,0,0,1,0,0],"masksToBounds":false,"rotation":0,"scale":1,"position":{"pointX":466.53158187866211,"pointY":271.34738159179688},"width":383.55603790283203,"sublayerTransform":[1,0,0,0,0,1,0,0,0,0,1,0,0,0,0,1],"contentsRect":{"y":0,"x":0,"width":1,"height":1},"opacity":1,"edgeAntialiasingMask":251658240,"height":187.29165649414062,"hidden":false,"anchorPoint":{"pointX":0.5,"pointY":0.5}},"layers":[{"animations":[{"additive":false,"timeOffset":0,"beginTime":0,"repeatCount":0,"fillMode":"both","duration":0.5,"autoreverses":false,"animations":[{"repeatCount":0,"removedOnCompletion":true,"from":{"scalar":1},"timingFunction":"EaseInEaseOut","additive":false,"timeOffset":0,"autoreverses":false,"property":"opacity","fillMode":"forwards","duration":0.16664999999999999,"beginTime":0,"to":{"scalar":0}},{"additive":false,"timeOffset":0,"beginTime":0.16664999999999999,"from":{"scalar":true},"repeatCount":0,"fillMode":"forwards","duration":0.33335000000000004,"autoreverses":false,"property":"hidden","to":{"scalar":true},"removedOnCompletion":true}],"removedOnCompletion":false}],"layers":[],"texturedRectangle":{"isBackgroundTexture":true,"singleTextureOpacity":1,"textureType":5,"textBaseline":0,"textXHeight":0,"isVerticalText":false},"initialState":{"affineTransform":[1,0,0,1,0,0],"masksToBounds":false,"rotation":0,"scale":1,"position":{"pointX":191.77801895141602,"pointY":93.645828247070312},"width":387,"sublayerTransform":[1,0,0,0,0,1,0,0,0,0,1,0,0,0,0,1],"contentsRect":{"y":0,"x":0,"width":1,"height":1},"opacity":1,"edgeAntialiasingMask":0,"height":190,"hidden":false,"anchorPoint":{"pointX":0.50008160692160752,"pointY":0.50182832416735201}},"texture":"7D0D6ADCFF5A1DA84875F396A1F3D49A"}]},{"animations":[{"additive":false,"timeOffset":0,"beginTime":0,"repeatCount":0,"fillMode":"both","duration":0.5,"autoreverses":false,"animations":[{"repeatCount":0,"removedOnCompletion":true,"from":{"scalar":0.0050000000000000001},"timingFunction":"EaseInEaseOut","additive":false,"timeOffset":0,"autoreverses":false,"property":"zPosition","fillMode":"both","duration":0.5,"beginTime":0,"to":{"scalar":0.0050000000000000001}}],"removedOnCompletion":false}],"initialState":{"affineTransform":[1,0,0,1,0,0],"masksToBounds":false,"rotation":0,"scale":1,"position":{"pointX":199.78756504968891,"pointY":546.02833614467841},"width":250,"sublayerTransform":[1,0,0,0,0,1,0,0,0,0,1,0,0,0,0,1],"contentsRect":{"y":0,"x":0,"width":1,"height":1},"opacity":1,"edgeAntialiasingMask":251658240,"height":91.757492065429688,"hidden":false,"anchorPoint":{"pointX":0.5,"pointY":0.5}},"layers":[{"animations":[{"additive":false,"timeOffset":0,"beginTime":0,"repeatCount":0,"fillMode":"both","duration":0.5,"autoreverses":false,"animations":[{"repeatCount":0,"removedOnCompletion":true,"from":{"scalar":1},"timingFunction":"EaseInEaseOut","additive":false,"timeOffset":0,"autoreverses":false,"property":"opacity","fillMode":"forwards","duration":0.16664999999999999,"beginTime":0,"to":{"scalar":0}},{"additive":false,"timeOffset":0,"beginTime":0.16664999999999999,"from":{"scalar":true},"repeatCount":0,"fillMode":"forwards","duration":0.33335000000000004,"autoreverses":false,"property":"hidden","to":{"scalar":true},"removedOnCompletion":true}],"removedOnCompletion":false}],"layers":[],"texturedRectangle":{"isBackgroundTexture":true,"singleTextureOpacity":1,"textureType":5,"textBaseline":0,"textXHeight":0,"isVerticalText":false},"initialState":{"affineTransform":[1,0,0,1,0,0],"masksToBounds":false,"rotation":0,"scale":1,"position":{"pointX":100,"pointY":45.878746032714844},"width":205,"sublayerTransform":[1,0,0,0,0,1,0,0,0,0,1,0,0,0,0,1],"contentsRect":{"y":0,"x":0,"width":1,"height":1},"opacity":1,"edgeAntialiasingMask":0,"height":96,"hidden":false,"anchorPoint":{"pointX":0.50140275633994591,"pointY":0.50029516817373343}},"texture":"2E7045BD920F3487C77D8EABFECE1D2D"}]},{"animations":[{"additive":false,"timeOffset":0,"beginTime":0,"repeatCount":0,"fillMode":"both","duration":0.5,"autoreverses":false,"animations":[{"repeatCount":0,"removedOnCompletion":true,"from":{"scalar":0.0060000000000000001},"timingFunction":"EaseInEaseOut","additive":false,"timeOffset":0,"autoreverses":false,"property":"zPosition","fillMode":"both","duration":0.5,"beginTime":0,"to":{"scalar":0.0060000000000000001}}],"removedOnCompletion":false}],"initialState":{"affineTransform":[1,0,0,1,0,0],"masksToBounds":false,"rotation":0,"scale":1,"position":{"pointX":466.5315825343132,"pointY":546.18106079101562},"width":383.55605447292328,"sublayerTransform":[1,0,0,0,0,1,0,0,0,0,1,0,0,0,0,1],"contentsRect":{"y":0,"x":0,"width":1,"height":1},"opacity":1,"edgeAntialiasingMask":251658240,"height":318.430419921875,"hidden":false,"anchorPoint":{"pointX":0.5,"pointY":0.5}},"layers":[{"animations":[{"additive":false,"timeOffset":0,"beginTime":0,"repeatCount":0,"fillMode":"both","duration":0.5,"autoreverses":false,"animations":[{"repeatCount":0,"removedOnCompletion":true,"from":{"scalar":1},"timingFunction":"EaseInEaseOut","additive":false,"timeOffset":0,"autoreverses":false,"property":"opacity","fillMode":"forwards","duration":0.16664999999999999,"beginTime":0,"to":{"scalar":0}},{"additive":false,"timeOffset":0,"beginTime":0.16664999999999999,"from":{"scalar":true},"repeatCount":0,"fillMode":"forwards","duration":0.33335000000000004,"autoreverses":false,"property":"hidden","to":{"scalar":true},"removedOnCompletion":true}],"removedOnCompletion":false}],"layers":[],"texturedRectangle":{"isBackgroundTexture":true,"singleTextureOpacity":1,"textureType":5,"textBaseline":0,"textXHeight":0,"isVerticalText":false},"initialState":{"affineTransform":[1,0,0,1,0,0],"masksToBounds":false,"rotation":0,"scale":1,"position":{"pointX":191.77802723646164,"pointY":159.2152099609375},"width":387,"sublayerTransform":[1,0,0,0,0,1,0,0,0,0,1,0,0,0,0,1],"contentsRect":{"y":0,"x":0,"width":1,"height":1},"opacity":1,"edgeAntialiasingMask":0,"height":322,"hidden":false,"anchorPoint":{"pointX":0.50008160861579642,"pointY":0.50056230059321627}},"texture":"A8DB8D9536F81A2527E0B05BA8FCC94D"}]},{"animations":[{"additive":false,"timeOffset":0,"beginTime":0,"repeatCount":0,"fillMode":"both","duration":0.5,"autoreverses":false,"animations":[{"repeatCount":0,"removedOnCompletion":true,"from":{"scalar":0.0070000000000000001},"timingFunction":"EaseInEaseOut","additive":false,"timeOffset":0,"autoreverses":false,"property":"zPosition","fillMode":"both","duration":0.5,"beginTime":0,"to":{"scalar":0.0070000000000000001}}],"removedOnCompletion":false}],"initialState":{"affineTransform":[1,0,0,1,0,0],"masksToBounds":false,"rotation":0,"scale":1,"position":{"pointX":199.78756504968891,"pointY":860.17540035366278},"width":250,"sublayerTransform":[1,0,0,0,0,1,0,0,0,0,1,0,0,0,0,1],"contentsRect":{"y":0,"x":0,"width":1,"height":1},"opacity":1,"edgeAntialiasingMask":251658240,"height":91.757492065429688,"hidden":false,"anchorPoint":{"pointX":0.5,"pointY":0.5}},"layers":[{"animations":[{"additive":false,"timeOffset":0,"beginTime":0,"repeatCount":0,"fillMode":"both","duration":0.5,"autoreverses":false,"animations":[{"repeatCount":0,"removedOnCompletion":true,"from":{"texture":"D1BCC90F4A817BAEF10B4EC9B04D169D"},"timingFunction":"EaseInEaseOut","additive":false,"timeOffset":0,"autoreverses":false,"property":"contents","fillMode":"both","duration":0.5,"beginTime":0,"to":{"texture":"6B879764B608788B7470C03483FC0DD4"}},{"repeatCount":0,"removedOnCompletion":true,"from":{"pointX":0,"pointY":0},"timingFunction":"EaseInEaseOut","additive":false,"timeOffset":0,"autoreverses":false,"property":"transform.translation","fillMode":"both","duration":0.5,"beginTime":0,"to":{"pointX":342.99999999999994,"pointY":-692}}],"removedOnCompletion":false}],"layers":[],"texturedRectangle":{"isBackgroundTexture":true,"singleTextureOpacity":1,"textureType":5,"textBaseline":0,"textXHeight":0,"isVerticalText":false},"initialState":{"affineTransform":[1,0,0,1,0,0],"masksToBounds":false,"rotation":0,"scale":1,"position":{"pointX":100,"pointY":45.878746032714844},"width":205,"sublayerTransform":[1,0,0,0,0,1,0,0,0,0,1,0,0,0,0,1],"contentsRect":{"y":0,"x":0,"width":1,"height":1},"opacity":1,"edgeAntialiasingMask":0,"height":97,"hidden":false,"anchorPoint":{"pointX":0.50140275633994591,"pointY":0.49665361189343071}},"texture":"D1BCC90F4A817BAEF10B4EC9B04D169D"}]},{"animations":[{"additive":false,"timeOffset":0,"beginTime":0,"repeatCount":0,"fillMode":"both","duration":0.5,"autoreverses":false,"animations":[{"repeatCount":0,"removedOnCompletion":true,"from":{"scalar":0.0080000000000000002},"timingFunction":"EaseInEaseOut","additive":false,"timeOffset":0,"autoreverses":false,"property":"zPosition","fillMode":"both","duration":0.5,"beginTime":0,"to":{"scalar":0.0080000000000000002}}],"removedOnCompletion":false}],"initialState":{"affineTransform":[1,0,0,1,0,0],"masksToBounds":false,"rotation":0,"scale":1,"position":{"pointX":466.53157806396484,"pointY":860.51001739501953},"width":383.55604553222656,"sublayerTransform":[1,0,0,0,0,1,0,0,0,0,1,0,0,0,0,1],"contentsRect":{"y":0,"x":0,"width":1,"height":1},"opacity":1,"edgeAntialiasingMask":251658240,"height":266.89308166503906,"hidden":false,"anchorPoint":{"pointX":0.5,"pointY":0.5}},"layers":[{"animations":[{"additive":false,"timeOffset":0,"beginTime":0,"repeatCount":0,"fillMode":"both","duration":0.5,"autoreverses":false,"animations":[{"repeatCount":0,"removedOnCompletion":true,"from":{"scalar":1},"timingFunction":"EaseInEaseOut","additive":false,"timeOffset":0,"autoreverses":false,"property":"opacity","fillMode":"forwards","duration":0.16664999999999999,"beginTime":0,"to":{"scalar":0}},{"additive":false,"timeOffset":0,"beginTime":0.16664999999999999,"from":{"scalar":true},"repeatCount":0,"fillMode":"forwards","duration":0.33335000000000004,"autoreverses":false,"property":"hidden","to":{"scalar":true},"removedOnCompletion":true}],"removedOnCompletion":false}],"layers":[],"texturedRectangle":{"isBackgroundTexture":true,"singleTextureOpacity":1,"textureType":5,"textBaseline":0,"textXHeight":0,"isVerticalText":false},"initialState":{"affineTransform":[1,0,0,1,0,0],"masksToBounds":false,"rotation":0,"scale":1,"position":{"pointX":191.77802276611328,"pointY":133.44654083251953},"width":387,"sublayerTransform":[1,0,0,0,0,1,0,0,0,0,1,0,0,0,0,1],"contentsRect":{"y":0,"x":0,"width":1,"height":1},"opacity":1,"edgeAntialiasingMask":0,"height":269,"hidden":false,"anchorPoint":{"pointX":0.50008159706450861,"pointY":0.50003723938668976}},"texture":"4A112B40B3884597F33BB6F30BFED3E9"}]},{"animations":[{"additive":false,"timeOffset":0,"beginTime":0,"repeatCount":0,"fillMode":"both","duration":0.5,"autoreverses":false,"animations":[{"repeatCount":0,"removedOnCompletion":true,"from":{"scalar":0.0090000000000000011},"timingFunction":"EaseInEaseOut","additive":false,"timeOffset":0,"autoreverses":false,"property":"zPosition","fillMode":"both","duration":0.5,"beginTime":0,"to":{"scalar":0.0090000000000000011}}],"removedOnCompletion":false}],"initialState":{"affineTransform":[1,0,0,1,0,0],"masksToBounds":false,"rotation":0,"scale":1,"position":{"pointX":1024.4200897220485,"pointY":231.34256431655558},"width":352.28836059570324,"sublayerTransform":[1,0,0,0,0,1,0,0,0,0,1,0,0,0,0,1],"contentsRect":{"y":0,"x":0,"width":1,"height":1},"opacity":1,"edgeAntialiasingMask":251658240,"height":376.15777587890625,"hidden":false,"anchorPoint":{"pointX":0.5,"pointY":0.5}},"layers":[{"animations":[{"additive":false,"timeOffset":0,"beginTime":0,"repeatCount":0,"fillMode":"both","duration":0.5,"autoreverses":false,"animations":[{"repeatCount":0,"removedOnCompletion":true,"from":{"scalar":1},"timingFunction":"EaseInEaseOut","additive":false,"timeOffset":0,"autoreverses":false,"property":"transform.scale.x","fillMode":"both","duration":0.5,"beginTime":0,"to":{"scalar":1.2954545454545454}},{"repeatCount":0,"removedOnCompletion":true,"from":{"scalar":1},"timingFunction":"EaseInEaseOut","additive":false,"timeOffset":0,"autoreverses":false,"property":"transform.scale.y","fillMode":"both","duration":0.5,"beginTime":0,"to":{"scalar":1.0327868852459017}},{"repeatCount":0,"removedOnCompletion":true,"from":{"texture":"87C15DFF8EDFD93167001BD43D51C037"},"timingFunction":"EaseInEaseOut","additive":false,"timeOffset":0,"autoreverses":false,"property":"contents","fillMode":"both","duration":0.33334999999999998,"beginTime":0,"to":{"texture":"C6B68B8849F70C492EB2F1F2F2E8219F"}},{"repeatCount":0,"removedOnCompletion":true,"from":{"pointX":0,"pointY":0},"timingFunction":"EaseInEaseOut","additive":false,"timeOffset":0,"autoreverses":false,"property":"transform.translation","fillMode":"both","duration":0.5,"beginTime":0,"to":{"pointX":551.0000000001088,"pointY":-150.0148929308032}}],"removedOnCompletion":false}],"layers":[],"texturedRectangle":{"isBackgroundTexture":true,"singleTextureOpacity":1,"textureType":5,"textBaseline":0,"textXHeight":0,"isVerticalText":false},"initialState":{"affineTransform":[1,0,0,1,0,0],"masksToBounds":false,"rotation":0,"scale":1,"position":{"pointX":111.72409057617176,"pointY":309.78208923339844},"width":528,"sublayerTransform":[1,0,0,0,0,1,0,0,0,0,1,0,0,0,0,1],"contentsRect":{"y":0,"x":0,"width":1,"height":1},"opacity":1,"edgeAntialiasingMask":0,"height":305,"hidden":false,"anchorPoint":{"pointX":0.50000000000069811,"pointY":0.49851070691967508}},"texture":"87C15DFF8EDFD93167001BD43D51C037"}]},{"animations":[{"additive":false,"timeOffset":0,"beginTime":0,"repeatCount":0,"fillMode":"both","duration":0.5,"autoreverses":false,"animations":[{"repeatCount":0,"removedOnCompletion":true,"from":{"scalar":0.01},"timingFunction":"EaseInEaseOut","additive":false,"timeOffset":0,"autoreverses":false,"property":"zPosition","fillMode":"both","duration":0.5,"beginTime":0,"to":{"scalar":0.01}}],"removedOnCompletion":false}],"initialState":{"affineTransform":[1,0,0,1,0,0],"masksToBounds":false,"rotation":0,"scale":1,"position":{"pointX":1024.420089705769,"pointY":546.4894425094642},"width":352.28836059570301,"sublayerTransform":[1,0,0,0,0,1,0,0,0,0,1,0,0,0,0,1],"contentsRect":{"y":0,"x":0,"width":1,"height":1},"opacity":1,"edgeAntialiasingMask":251658240,"height":376.15777587890625,"hidden":false,"anchorPoint":{"pointX":0.5,"pointY":0.5}},"layers":[{"animations":[{"additive":false,"timeOffset":0,"beginTime":0,"repeatCount":0,"fillMode":"both","duration":0.5,"autoreverses":false,"animations":[{"repeatCount":0,"removedOnCompletion":true,"from":{"scalar":1},"timingFunction":"EaseInEaseOut","additive":false,"timeOffset":0,"autoreverses":false,"property":"opacity","fillMode":"forwards","duration":0.16664999999999999,"beginTime":0,"to":{"scalar":0}},{"additive":false,"timeOffset":0,"beginTime":0.16664999999999999,"from":{"scalar":true},"repeatCount":0,"fillMode":"forwards","duration":0.33335000000000004,"autoreverses":false,"property":"hidden","to":{"scalar":true},"removedOnCompletion":true}],"removedOnCompletion":false}],"layers":[],"texturedRectangle":{"isBackgroundTexture":true,"singleTextureOpacity":1,"textureType":5,"textBaseline":0,"textXHeight":0,"isVerticalText":false},"initialState":{"affineTransform":[1,0,0,1,0,0],"masksToBounds":false,"rotation":0,"scale":1,"position":{"pointX":111.72409057617188,"pointY":276.40636444091797},"width":528,"sublayerTransform":[1,0,0,0,0,1,0,0,0,0,1,0,0,0,0,1],"contentsRect":{"y":0,"x":0,"width":1,"height":1},"opacity":1,"edgeAntialiasingMask":0,"height":238,"hidden":false,"anchorPoint":{"pointX":0.49999999996986633,"pointY":0.49923075214676066}},"texture":"8D8076FC571C884B99B78997664A31AB"}]},{"animations":[{"additive":false,"timeOffset":0,"beginTime":0,"repeatCount":0,"fillMode":"both","duration":0.5,"autoreverses":false,"animations":[{"repeatCount":0,"removedOnCompletion":true,"from":{"scalar":0.010999999999999999},"timingFunction":"EaseInEaseOut","additive":false,"timeOffset":0,"autoreverses":false,"property":"zPosition","fillMode":"both","duration":0.5,"beginTime":0,"to":{"scalar":0.010999999999999999}}],"removedOnCompletion":false}],"initialState":{"affineTransform":[1,0,0,1,0,0],"masksToBounds":false,"rotation":0,"scale":1,"position":{"pointX":1571.0955551465038,"pointY":503.46470681265339},"width":618.810302734375,"sublayerTransform":[1,0,0,0,0,1,0,0,0,0,1,0,0,0,0,1],"contentsRect":{"y":0,"x":0,"width":1,"height":1},"opacity":1,"edgeAntialiasingMask":251658240,"height":191.83839416503906,"hidden":false,"anchorPoint":{"pointX":0.5,"pointY":0.5}},"layers":[{"animations":[{"additive":false,"timeOffset":0,"beginTime":0,"repeatCount":0,"fillMode":"both","duration":0.5,"autoreverses":false,"animations":[{"repeatCount":0,"removedOnCompletion":true,"from":{"scalar":1},"timingFunction":"EaseInEaseOut","additive":false,"timeOffset":0,"autoreverses":false,"property":"opacity","fillMode":"forwards","duration":0.16664999999999999,"beginTime":0,"to":{"scalar":0}},{"additive":false,"timeOffset":0,"beginTime":0.16664999999999999,"from":{"scalar":true},"repeatCount":0,"fillMode":"forwards","duration":0.33335000000000004,"autoreverses":false,"property":"hidden","to":{"scalar":true},"removedOnCompletion":true}],"removedOnCompletion":false}],"layers":[],"texturedRectangle":{"isBackgroundTexture":true,"singleTextureOpacity":1,"textureType":5,"textBaseline":0,"textXHeight":0,"isVerticalText":false},"initialState":{"affineTransform":[1,0,0,1,0,0],"masksToBounds":false,"rotation":0,"scale":1,"position":{"pointX":309.4051513671875,"pointY":95.919197082519531},"width":624,"sublayerTransform":[1,0,0,0,0,1,0,0,0,0,1,0,0,0,0,1],"contentsRect":{"y":0,"x":0,"width":1,"height":1},"opacity":1,"edgeAntialiasingMask":0,"height":197,"hidden":false,"anchorPoint":{"pointX":0.50015313324760224,"pointY":0.49982084676473804}},"texture":"1796028C98209D0165F52AB38FB587DF"}]},{"animations":[{"additive":false,"timeOffset":0,"beginTime":0,"repeatCount":0,"fillMode":"both","duration":0.5,"autoreverses":false,"animations":[{"repeatCount":0,"removedOnCompletion":true,"from":{"scalar":0.012},"timingFunction":"EaseInEaseOut","additive":false,"timeOffset":0,"autoreverses":false,"property":"zPosition","fillMode":"both","duration":0.5,"beginTime":0,"to":{"scalar":0.012}}],"removedOnCompletion":false}],"initialState":{"affineTransform":[1,0,0,1,0,0],"masksToBounds":false,"rotation":0,"scale":1,"position":{"pointX":1571.0955551302245,"pointY":793.37098727918237},"width":618.810302734375,"sublayerTransform":[1,0,0,0,0,1,0,0,0,0,1,0,0,0,0,1],"contentsRect":{"y":0,"x":0,"width":1,"height":1},"opacity":1,"edgeAntialiasingMask":251658240,"height":264.22378540039062,"hidden":false,"anchorPoint":{"pointX":0.5,"pointY":0.5}},"layers":[{"animations":[{"additive":false,"timeOffset":0,"beginTime":0,"repeatCount":0,"fillMode":"both","duration":0.5,"autoreverses":false,"animations":[{"repeatCount":0,"removedOnCompletion":true,"from":{"scalar":1},"timingFunction":"EaseInEaseOut","additive":false,"timeOffset":0,"autoreverses":false,"property":"opacity","fillMode":"forwards","duration":0.16664999999999999,"beginTime":0,"to":{"scalar":0}},{"additive":false,"timeOffset":0,"beginTime":0.16664999999999999,"from":{"scalar":true},"repeatCount":0,"fillMode":"forwards","duration":0.33335000000000004,"autoreverses":false,"property":"hidden","to":{"scalar":true},"removedOnCompletion":true}],"removedOnCompletion":false}],"layers":[],"texturedRectangle":{"isBackgroundTexture":true,"singleTextureOpacity":1,"textureType":5,"textBaseline":0,"textXHeight":0,"isVerticalText":false},"initialState":{"affineTransform":[1,0,0,1,0,0],"masksToBounds":false,"rotation":0,"scale":1,"position":{"pointX":309.4051513671875,"pointY":132.11189270019531},"width":624,"sublayerTransform":[1,0,0,0,0,1,0,0,0,0,1,0,0,0,0,1],"contentsRect":{"y":0,"x":0,"width":1,"height":1},"opacity":1,"edgeAntialiasingMask":0,"height":269,"hidden":false,"anchorPoint":{"pointX":0.50015313322151367,"pointY":0.49952039880736943}},"texture":"E3ADDBBFD8171082E38ADE95F01AB209"}]},{"animations":[{"additive":false,"timeOffset":0,"beginTime":0,"repeatCount":0,"fillMode":"both","duration":0.5,"autoreverses":false,"animations":[{"repeatCount":0,"removedOnCompletion":true,"from":{"scalar":0.013000000000000001},"timingFunction":"EaseInEaseOut","additive":false,"timeOffset":0,"autoreverses":false,"property":"zPosition","fillMode":"both","duration":0.5,"beginTime":0,"to":{"scalar":0.013000000000000001}}],"removedOnCompletion":false}],"initialState":{"affineTransform":[1,0,0,1,0,0],"masksToBounds":false,"rotation":0,"scale":1,"position":{"pointX":1570.0954939921382,"pointY":258.774498462677},"width":420.1453857421875,"sublayerTransform":[1,0,0,0,0,1,0,0,0,0,1,0,0,0,0,1],"contentsRect":{"y":0,"x":0,"width":1,"height":1},"opacity":1,"edgeAntialiasingMask":251658240,"height":173.79164123535156,"hidden":false,"anchorPoint":{"pointX":0.5,"pointY":0.5}},"layers":[{"animations":[{"additive":false,"timeOffset":0,"beginTime":0,"repeatCount":0,"fillMode":"both","duration":0.5,"autoreverses":false,"animations":[{"repeatCount":0,"removedOnCompletion":true,"from":{"scalar":1},"timingFunction":"EaseInEaseOut","additive":false,"timeOffset":0,"autoreverses":false,"property":"opacity","fillMode":"forwards","duration":0.16664999999999999,"beginTime":0,"to":{"scalar":0}},{"additive":false,"timeOffset":0,"beginTime":0.16664999999999999,"from":{"scalar":true},"repeatCount":0,"fillMode":"forwards","duration":0.33335000000000004,"autoreverses":false,"property":"hidden","to":{"scalar":true},"removedOnCompletion":true}],"removedOnCompletion":false}],"layers":[],"texturedRectangle":{"isBackgroundTexture":true,"singleTextureOpacity":1,"textureType":5,"textBaseline":0,"textXHeight":0,"isVerticalText":false},"initialState":{"affineTransform":[1,0,0,1,0,0],"masksToBounds":false,"rotation":0,"scale":1,"position":{"pointX":210.07269287109375,"pointY":86.895820617675781},"width":425,"sublayerTransform":[1,0,0,0,0,1,0,0,0,0,1,0,0,0,0,1],"contentsRect":{"y":0,"x":0,"width":1,"height":1},"opacity":1,"edgeAntialiasingMask":0,"height":179,"hidden":false,"anchorPoint":{"pointX":0.49904822115797232,"pointY":0.50153351096467602}},"texture":"99B4D0FF28E2692CD0C57104DAC27CED"}]},{"animations":[{"additive":false,"timeOffset":0,"beginTime":0,"repeatCount":0,"fillMode":"both","duration":0.5,"autoreverses":false,"animations":[{"repeatCount":0,"removedOnCompletion":true,"from":{"scalar":0.014},"timingFunction":"EaseInEaseOut","additive":false,"timeOffset":0,"autoreverses":false,"property":"zPosition","fillMode":"both","duration":0.5,"beginTime":0,"to":{"scalar":0.014}}],"removedOnCompletion":false}],"initialState":{"affineTransform":[1,0,0,1,0,0],"masksToBounds":false,"rotation":0,"scale":1,"position":{"pointX":1024.4200807699231,"pointY":794.88487106583364},"width":352.28836059570324,"sublayerTransform":[1,0,0,0,0,1,0,0,0,0,1,0,0,0,0,1],"contentsRect":{"y":0,"x":0,"width":1,"height":1},"opacity":1,"edgeAntialiasingMask":251658240,"height":376.15777587890625,"hidden":false,"anchorPoint":{"pointX":0.5,"pointY":0.5}},"layers":[{"animations":[{"additive":false,"timeOffset":0,"beginTime":0,"repeatCount":0,"fillMode":"both","duration":0.5,"autoreverses":false,"animations":[{"repeatCount":0,"removedOnCompletion":true,"from":{"scalar":1},"timingFunction":"EaseInEaseOut","additive":false,"timeOffset":0,"autoreverses":false,"property":"opacity","fillMode":"forwards","duration":0.16664999999999999,"beginTime":0,"to":{"scalar":0}},{"additive":false,"timeOffset":0,"beginTime":0.16664999999999999,"from":{"scalar":true},"repeatCount":0,"fillMode":"forwards","duration":0.33335000000000004,"autoreverses":false,"property":"hidden","to":{"scalar":true},"removedOnCompletion":true}],"removedOnCompletion":false}],"layers":[],"texturedRectangle":{"isBackgroundTexture":true,"singleTextureOpacity":1,"textureType":5,"textBaseline":0,"textXHeight":0,"isVerticalText":false},"initialState":{"affineTransform":[1,0,0,1,0,0],"masksToBounds":false,"rotation":0,"scale":1,"position":{"pointX":111.72409057617188,"pointY":276.40636444091797},"width":528,"sublayerTransform":[1,0,0,0,0,1,0,0,0,0,1,0,0,0,0,1],"contentsRect":{"y":0,"x":0,"width":1,"height":1},"opacity":1,"edgeAntialiasingMask":0,"height":238,"hidden":false,"anchorPoint":{"pointX":0.49999998304591525,"pointY":0.50089221666932138}},"texture":"B9AA89F1E301910A2B675E6B21148B58"}]},{"animations":[{"additive":false,"timeOffset":0,"beginTime":0,"repeatCount":0,"fillMode":"both","duration":0.5,"autoreverses":false,"animations":[{"repeatCount":0,"removedOnCompletion":true,"from":{"scalar":0.014999999999999999},"timingFunction":"EaseInEaseOut","additive":false,"timeOffset":0,"autoreverses":false,"property":"zPosition","fillMode":"both","duration":0.5,"beginTime":0,"to":{"scalar":0.014999999999999999}}],"removedOnCompletion":false}],"initialState":{"affineTransform":[1,0,0,1,0,0],"masksToBounds":false,"rotation":0,"scale":1,"position":{"pointX":517.71886877409565,"pointY":702.31017504539955},"width":866.2203369140625,"sublayerTransform":[1,0,0,0,0,1,0,0,0,0,1,0,0,0,0,1],"contentsRect":{"y":0,"x":0,"width":1,"height":1},"opacity":1,"edgeAntialiasingMask":251658240,"height":560.9205322265625,"hidden":false,"anchorPoint":{"pointX":0.5,"pointY":0.5}},"layers":[{"animations":[{"additive":false,"timeOffset":0,"beginTime":0,"repeatCount":0,"fillMode":"both","duration":0.5,"autoreverses":false,"animations":[{"repeatCount":0,"removedOnCompletion":true,"from":{"scalar":0},"timingFunction":"EaseInEaseOut","additive":false,"timeOffset":0,"autoreverses":false,"property":"opacity","fillMode":"both","duration":0.16664999999999999,"beginTime":0.33335000000000004,"to":{"scalar":1}},{"additive":false,"timeOffset":0,"beginTime":0.33335000000000004,"from":{"scalar":false},"repeatCount":0,"fillMode":"forwards","duration":0.16664999999999996,"autoreverses":false,"property":"hidden","to":{"scalar":false},"removedOnCompletion":true}],"removedOnCompletion":false}],"layers":[],"texturedRectangle":{"isBackgroundTexture":true,"singleTextureOpacity":1,"textureType":5,"textBaseline":0,"textXHeight":0,"isVerticalText":false},"initialState":{"affineTransform":[1,0,0,1,0,0],"masksToBounds":false,"rotation":0,"scale":1,"position":{"pointX":433.11016845703119,"pointY":280.46026611328131},"width":869,"sublayerTransform":[1,0,0,0,0,1,0,0,0,0,1,0,0,0,0,1],"contentsRect":{"y":0,"x":0,"width":1,"height":1},"opacity":1,"edgeAntialiasingMask":0,"height":564,"hidden":true,"anchorPoint":{"pointX":0.50025186280103062,"pointY":0.50054995575425454}},"texture":"92F080D6EFD25320C74C7DA152EDEF71"}]},{"animations":[{"additive":false,"timeOffset":0,"beginTime":0,"repeatCount":0,"fillMode":"both","duration":0.5,"autoreverses":false,"animations":[{"repeatCount":0,"removedOnCompletion":true,"from":{"scalar":0.016},"timingFunction":"EaseInEaseOut","additive":false,"timeOffset":0,"autoreverses":false,"property":"zPosition","fillMode":"both","duration":0.5,"beginTime":0,"to":{"scalar":0.016}}],"removedOnCompletion":false}],"initialState":{"affineTransform":[1,0,0,1,0,0],"masksToBounds":false,"rotation":0,"scale":1,"position":{"pointX":1401.8605545725923,"pointY":702.3101750438293},"width":866.21875000000011,"sublayerTransform":[1,0,0,0,0,1,0,0,0,0,1,0,0,0,0,1],"contentsRect":{"y":0,"x":0,"width":1,"height":1},"opacity":1,"edgeAntialiasingMask":251658240,"height":554.8125,"hidden":false,"anchorPoint":{"pointX":0.5,"pointY":0.5}},"layers":[{"animations":[{"additive":false,"timeOffset":0,"beginTime":0,"repeatCount":0,"fillMode":"both","duration":0.5,"autoreverses":false,"animations":[{"repeatCount":0,"removedOnCompletion":true,"from":{"scalar":0},"timingFunction":"EaseInEaseOut","additive":false,"timeOffset":0,"autoreverses":false,"property":"opacity","fillMode":"both","duration":0.16664999999999999,"beginTime":0.33335000000000004,"to":{"scalar":1}},{"additive":false,"timeOffset":0,"beginTime":0.33335000000000004,"from":{"scalar":false},"repeatCount":0,"fillMode":"forwards","duration":0.16664999999999996,"autoreverses":false,"property":"hidden","to":{"scalar":false},"removedOnCompletion":true}],"removedOnCompletion":false}],"layers":[],"texturedRectangle":{"isBackgroundTexture":true,"singleTextureOpacity":1,"textureType":5,"textBaseline":0,"textXHeight":0,"isVerticalText":false},"initialState":{"affineTransform":[1,0,0,1,0,0],"masksToBounds":false,"rotation":0,"scale":1,"position":{"pointX":433.10585728894887,"pointY":277.403215050028},"width":869,"sublayerTransform":[1,0,0,0,0,1,0,0,0,0,1,0,0,0,0,1],"contentsRect":{"y":0,"x":0,"width":1,"height":1},"opacity":1,"edgeAntialiasingMask":0,"height":558,"hidden":true,"anchorPoint":{"pointX":0.50041085944941432,"pointY":0.50055043027572987}},"texture":"78B2571B4C942879C0A8C8D665EEA93B"}]},{"animations":[{"additive":false,"timeOffset":0,"beginTime":0,"repeatCount":0,"fillMode":"both","duration":0.5,"autoreverses":false,"animations":[{"repeatCount":0,"removedOnCompletion":true,"from":{"scalar":0.017000000000000001},"timingFunction":"EaseInEaseOut","additive":false,"timeOffset":0,"autoreverses":false,"property":"zPosition","fillMode":"both","duration":0.5,"beginTime":0,"to":{"scalar":0.017000000000000001}}],"removedOnCompletion":false}],"initialState":{"affineTransform":[1,0,0,1,0,0],"masksToBounds":false,"rotation":0,"scale":1,"position":{"pointX":559.23453246605141,"pointY":280.77283516631735},"width":980.53576660156239,"sublayerTransform":[1,0,0,0,0,1,0,0,0,0,1,0,0,0,0,1],"contentsRect":{"y":0,"x":0,"width":1,"height":1},"opacity":1,"edgeAntialiasingMask":251658240,"height":134.3441172087874,"hidden":false,"anchorPoint":{"pointX":0.5,"pointY":0.5}},"layers":[{"animations":[{"additive":false,"timeOffset":0,"beginTime":0,"repeatCount":0,"fillMode":"both","duration":0.5,"autoreverses":false,"animations":[{"repeatCount":0,"removedOnCompletion":true,"from":{"scalar":0},"timingFunction":"EaseInEaseOut","additive":false,"timeOffset":0,"autoreverses":false,"property":"opacity","fillMode":"both","duration":0.16664999999999999,"beginTime":0.33335000000000004,"to":{"scalar":1}},{"additive":false,"timeOffset":0,"beginTime":0.33335000000000004,"from":{"scalar":false},"repeatCount":0,"fillMode":"forwards","duration":0.16664999999999996,"autoreverses":false,"property":"hidden","to":{"scalar":false},"removedOnCompletion":true}],"removedOnCompletion":false}],"layers":[],"texturedRectangle":{"singleTextureOpacity":1,"textXHeight":0,"shapePath":{"lineWidth":1,"flatness":0.59999999999999998,"lineCapStyle":0,"elements":[{"type":"MoveToPoint","points":[[452.76612967049175,1.6007765619236238]]},{"type":"AddLine","points":[[982.50241576683266,135.94489377071102]]},{"type":"AddLine","points":[[1.9666491652702689,135.94489377071102]]},{"type":"AddLine","points":[[452.76612967049175,1.6007765619236238]]},{"type":"CloseSubpath"},{"type":"MoveToPoint","points":[[452.76612967049175,1.6007765619236238]]}],"windingRule":0,"lineJoinStyle":0,"miterLimit":10},"isBackgroundTexture":true,"textBaseline":0,"isVerticalText":false,"textureType":5},"initialState":{"affineTransform":[1,0,0,1,0,0],"masksToBounds":false,"rotation":0,"scale":1,"position":{"pointX":490.26788330078114,"pointY":67.172058604393726},"width":984,"sublayerTransform":[1,0,0,0,0,1,0,0,0,0,1,0,0,0,0,1],"contentsRect":{"y":0,"x":0,"width":1,"height":1},"opacity":1,"edgeAntialiasingMask":0,"height":137,"hidden":true,"anchorPoint":{"pointX":0.50023834600208472,"pointY":0.50199149756436023}},"texture":"7F9169F746AA870A0DEF2212163E8B53"}]},{"animations":[{"additive":false,"timeOffset":0,"beginTime":0,"repeatCount":0,"fillMode":"both","duration":0.5,"autoreverses":false,"animations":[{"repeatCount":0,"removedOnCompletion":true,"from":{"scalar":0.018000000000000002},"timingFunction":"EaseInEaseOut","additive":false,"timeOffset":0,"autoreverses":false,"property":"zPosition","fillMode":"both","duration":0.5,"beginTime":0,"to":{"scalar":0.018000000000000002}}],"removedOnCompletion":false}],"initialState":{"affineTransform":[1,0,0,1,0,0],"masksToBounds":false,"rotation":0,"scale":1,"position":{"pointX":517.71886873992412,"pointY":384.89740137768382},"width":301.82842807842053,"sublayerTransform":[1,0,0,0,0,1,0,0,0,0,1,0,0,0,0,1],"contentsRect":{"y":0,"x":0,"width":1,"height":1},"opacity":1,"edgeAntialiasingMask":251658240,"height":45.82842784000195,"hidden":false,"anchorPoint":{"pointX":0.5,"pointY":0.5}},"layers":[{"animations":[{"additive":false,"timeOffset":0,"beginTime":0,"repeatCount":0,"fillMode":"both","duration":0.5,"autoreverses":false,"animations":[{"repeatCount":0,"removedOnCompletion":true,"from":{"scalar":0},"timingFunction":"EaseInEaseOut","additive":false,"timeOffset":0,"autoreverses":false,"property":"opacity","fillMode":"both","duration":0.16664999999999999,"beginTime":0.33335000000000004,"to":{"scalar":1}},{"additive":false,"timeOffset":0,"beginTime":0.33335000000000004,"from":{"scalar":false},"repeatCount":0,"fillMode":"forwards","duration":0.16664999999999996,"autoreverses":false,"property":"hidden","to":{"scalar":false},"removedOnCompletion":true}],"removedOnCompletion":false}],"layers":[],"texturedRectangle":{"singleTextureOpacity":1,"textXHeight":0,"shapePath":{"lineWidth":1,"flatness":0.59999999999999998,"lineCapStyle":0,"elements":[{"type":"MoveToPoint","points":[[3.2188682630869607,3.3974010200559519]]},{"type":"AddLine","points":[[302.21886921676128,3.3974010200559519]]},{"type":"AddLine","points":[[302.21886921676128,46.397401735311689]]},{"type":"AddLine","points":[[3.2188682630869607,46.397401735311689]]},{"type":"CloseSubpath"},{"type":"MoveToPoint","points":[[3.2188682630869607,3.3974010200559519]]}],"windingRule":0,"lineJoinStyle":0,"miterLimit":10},"isBackgroundTexture":true,"textBaseline":0,"isVerticalText":false,"textureType":5},"initialState":{"affineTransform":[1,0,0,1,0,0],"masksToBounds":false,"rotation":0,"scale":1,"position":{"pointX":150.91421356237311,"pointY":22.914213562373106},"width":305,"sublayerTransform":[1,0,0,0,0,1,0,0,0,0,1,0,0,0,0,1],"contentsRect":{"y":0,"x":0,"width":1,"height":1},"opacity":1,"edgeAntialiasingMask":0,"height":49,"hidden":true,"anchorPoint":{"pointX":0.50071760086258021,"pointY":0.50811022489910107}},"texture":"C01262779C34742FCAB4F9FA6FF78572"}]},{"animations":[{"additive":false,"timeOffset":0,"beginTime":0,"repeatCount":0,"fillMode":"both","duration":0.5,"autoreverses":false,"animations":[{"repeatCount":0,"removedOnCompletion":true,"from":{"scalar":0.019},"timingFunction":"EaseInEaseOut","additive":false,"timeOffset":0,"autoreverses":false,"property":"zPosition","fillMode":"both","duration":0.5,"beginTime":0,"to":{"scalar":0.019}}],"removedOnCompletion":false}],"initialState":{"affineTransform":[1,0,0,1,0,0],"masksToBounds":false,"rotation":0,"scale":1,"position":{"pointX":517.71886873992412,"pointY":384.89740137768382},"width":301.82842807842053,"sublayerTransform":[1,0,0,0,0,1,0,0,0,0,1,0,0,0,0,1],"contentsRect":{"y":0,"x":0,"width":1,"height":1},"opacity":1,"edgeAntialiasingMask":251658240,"height":45.82842784000195,"hidden":false,"anchorPoint":{"pointX":0.5,"pointY":0.5}},"layers":[{"animations":[{"additive":false,"timeOffset":0,"beginTime":0,"repeatCount":0,"fillMode":"both","duration":0.5,"autoreverses":false,"animations":[{"repeatCount":0,"removedOnCompletion":true,"from":{"scalar":0},"timingFunction":"EaseInEaseOut","additive":false,"timeOffset":0,"autoreverses":false,"property":"opacity","fillMode":"both","duration":0.16664999999999999,"beginTime":0.33335000000000004,"to":{"scalar":1}},{"additive":false,"timeOffset":0,"beginTime":0.33335000000000004,"from":{"scalar":false},"repeatCount":0,"fillMode":"forwards","duration":0.16664999999999996,"autoreverses":false,"property":"hidden","to":{"scalar":false},"removedOnCompletion":true}],"removedOnCompletion":false}],"layers":[],"texturedRectangle":{"singleTextureOpacity":1,"textXHeight":0.55384615384615388,"textBaseline":0.81682248012858871,"isBackgroundTexture":true,"isVerticalText":false,"textColor":[0.37036359310150146,0.37036353349685669,0.37036359310150146,1],"textureType":6},"initialState":{"affineTransform":[1,0,0,1,0,0],"masksToBounds":false,"rotation":0,"scale":1,"position":{"pointX":150.91421356237311,"pointY":22.914213562373106},"width":290,"sublayerTransform":[1,0,0,0,0,1,0,0,0,0,1,0,0,0,0,1],"contentsRect":{"y":0,"x":0,"width":1,"height":1},"opacity":1,"edgeAntialiasingMask":0,"height":26,"hidden":true,"anchorPoint":{"pointX":0.49903058021754126,"pointY":0.49605388538676737}},"texture":"9A6D3BC21262E5851D204FFA9173D32E"}]},{"animations":[{"additive":false,"timeOffset":0,"beginTime":0,"repeatCount":0,"fillMode":"both","duration":0.5,"autoreverses":false,"animations":[{"repeatCount":0,"removedOnCompletion":true,"from":{"scalar":0.02},"timingFunction":"EaseInEaseOut","additive":false,"timeOffset":0,"autoreverses":false,"property":"zPosition","fillMode":"both","duration":0.5,"beginTime":0,"to":{"scalar":0.02}}],"removedOnCompletion":false}],"initialState":{"affineTransform":[1,0,0,1,0,0],"masksToBounds":false,"rotation":0,"scale":1,"position":{"pointX":1401.860554575597,"pointY":391.55801176764993},"width":368.1644161231593,"sublayerTransform":[1,0,0,0,0,1,0,0,0,0,1,0,0,0,0,1],"contentsRect":{"y":0,"x":0,"width":1,"height":1},"opacity":1,"edgeAntialiasingMask":251658240,"height":48.028605151899228,"hidden":false,"anchorPoint":{"pointX":0.5,"pointY":0.5}},"layers":[{"animations":[{"additive":false,"timeOffset":0,"beginTime":0,"repeatCount":0,"fillMode":"both","duration":0.5,"autoreverses":false,"animations":[{"repeatCount":0,"removedOnCompletion":true,"from":{"scalar":0},"timingFunction":"EaseInEaseOut","additive":false,"timeOffset":0,"autoreverses":false,"property":"opacity","fillMode":"both","duration":0.16664999999999999,"beginTime":0.33335000000000004,"to":{"scalar":1}},{"additive":false,"timeOffset":0,"beginTime":0.33335000000000004,"from":{"scalar":false},"repeatCount":0,"fillMode":"forwards","duration":0.16664999999999996,"autoreverses":false,"property":"hidden","to":{"scalar":false},"removedOnCompletion":true}],"removedOnCompletion":false}],"layers":[],"texturedRectangle":{"singleTextureOpacity":1,"textXHeight":0,"shapePath":{"lineWidth":1,"flatness":0.59999999999999998,"lineCapStyle":0,"elements":[{"type":"MoveToPoint","points":[[3.192560076390464,2.9579227540734223]]},{"type":"AddLine","points":[[368.52854907480355,2.9579227540734223]]},{"type":"AddLine","points":[[368.52854907480355,48.158100781226437]]},{"type":"AddLine","points":[[3.192560076390464,48.158100781226437]]},{"type":"CloseSubpath"},{"type":"MoveToPoint","points":[[3.192560076390464,2.9579227540734223]]}],"windingRule":0,"lineJoinStyle":0,"miterLimit":10},"isBackgroundTexture":true,"textBaseline":0,"isVerticalText":false,"textureType":5},"initialState":{"affineTransform":[1,0,0,1,0,0],"masksToBounds":false,"rotation":0,"scale":1,"position":{"pointX":184.082213562373,"pointY":24.01430239713568},"width":371,"sublayerTransform":[1,0,0,0,0,1,0,0,0,0,1,0,0,0,0,1],"contentsRect":{"y":0,"x":0,"width":1,"height":1},"opacity":1,"edgeAntialiasingMask":0,"height":51,"hidden":true,"anchorPoint":{"pointX":0.50097186004417882,"pointY":0.50113748213403908}},"texture":"EDE3317141A20CA829F956C46062911A"}]},{"animations":[{"additive":false,"timeOffset":0,"beginTime":0,"repeatCount":0,"fillMode":"both","duration":0.5,"autoreverses":false,"animations":[{"repeatCount":0,"removedOnCompletion":true,"from":{"scalar":0.021000000000000001},"timingFunction":"EaseInEaseOut","additive":false,"timeOffset":0,"autoreverses":false,"property":"zPosition","fillMode":"both","duration":0.5,"beginTime":0,"to":{"scalar":0.021000000000000001}}],"removedOnCompletion":false}],"initialState":{"affineTransform":[1,0,0,1,0,0],"masksToBounds":false,"rotation":0,"scale":1,"position":{"pointX":1401.860554575597,"pointY":391.55801176764993},"width":368.1644161231593,"sublayerTransform":[1,0,0,0,0,1,0,0,0,0,1,0,0,0,0,1],"contentsRect":{"y":0,"x":0,"width":1,"height":1},"opacity":1,"edgeAntialiasingMask":251658240,"height":48.028605151899228,"hidden":false,"anchorPoint":{"pointX":0.5,"pointY":0.5}},"layers":[{"animations":[{"additive":false,"timeOffset":0,"beginTime":0,"repeatCount":0,"fillMode":"both","duration":0.5,"autoreverses":false,"animations":[{"repeatCount":0,"removedOnCompletion":true,"from":{"scalar":0},"timingFunction":"EaseInEaseOut","additive":false,"timeOffset":0,"autoreverses":false,"property":"opacity","fillMode":"both","duration":0.16664999999999999,"beginTime":0.33335000000000004,"to":{"scalar":1}},{"additive":false,"timeOffset":0,"beginTime":0.33335000000000004,"from":{"scalar":false},"repeatCount":0,"fillMode":"forwards","duration":0.16664999999999996,"autoreverses":false,"property":"hidden","to":{"scalar":false},"removedOnCompletion":true}],"removedOnCompletion":false}],"layers":[],"texturedRectangle":{"singleTextureOpacity":1,"textXHeight":0.55384615384615388,"textBaseline":0.84608014949561239,"isBackgroundTexture":true,"isVerticalText":false,"textColor":[0.37036359310150146,0.37036353349685669,0.37036359310150146,1],"textureType":6},"initialState":{"affineTransform":[1,0,0,1,0,0],"masksToBounds":false,"rotation":0,"scale":1,"position":{"pointX":184.082213562373,"pointY":24.01430239713568},"width":356,"sublayerTransform":[1,0,0,0,0,1,0,0,0,0,1,0,0,0,0,1],"contentsRect":{"y":0,"x":0,"width":1,"height":1},"opacity":1,"edgeAntialiasingMask":0,"height":26,"hidden":true,"anchorPoint":{"pointX":0.49960831482132123,"pointY":0.48300044572446138}},"texture":"DE7E69848A2A2C788BBBE86BB17CBA75"}]}]},"effects":[],"duration":0.5,"type":"transition","attributes":{"direction":0},"name":"apple:magic-move-implied-motion-path","objectID":"0"}],"automaticPlay":false,"hyperlinks":[],"accessibility":[{"text":"Home-page","targetRectangle":{"y":249.84734449505072,"x":101.88756614641437,"width":145.79999999999998,"height":43}},{"text":"","targetRectangle":{"y":680.49902395701974,"x":1422.048922840338,"width":288,"height":33}},{"text":"","targetRectangle":{"y":191.11862248182297,"x":1446.0420877535823,"width":240,"height":33}},{"text":"component-note-card1.png","targetRectangle":{"y":714.24292026258081,"x":1284.6617637312224,"width":273,"height":196}},{"text":" ","targetRectangle":{"y":281.76128074721953,"x":718.16256712419056,"width":459.99000000000012,"height":82.050198817247804}},{"text":" ","targetRectangle":{"y":398.31147753790941,"x":718.16256712419056,"width":459.99000000000012,"height":82.050198817247804}},{"text":"","targetRectangle":{"y":221.26407346324595,"x":889.99999952353153,"width":140.00000000000011,"height":49}},{"text":"component-home-card.png","targetRectangle":{"y":454.84340706900105,"x":1276.9423569043163,"width":588.3125,"height":128.54624938964844}},{"text":"component-note-card2.png","targetRectangle":{"y":714.24292026258081,"x":1574.4360798036864,"width":273,"height":196}},{"text":"","targetRectangle":{"y":602.90815894012826,"x":718.16256712276129,"width":479.99999999999989,"height":117.59999799728394}},{"text":"","targetRectangle":{"y":423.41120204761967,"x":1439.098605950642,"width":264,"height":33}},{"text":"page-subpage.png","targetRectangle":{"y":386.96585083007812,"x":358.30960083007812,"width":300.00000894069672,"height":318.125}},{"text":"","targetRectangle":{"y":52.410270690917997,"x":836.24999997206055,"width":247.50000005587935,"height":70}},{"text":"User Interface","targetRectangle":{"y":108.41027152538302,"x":784.19999992176918,"width":351.10000015646233,"height":72}},{"text":" 2024-01-21 7.59.59.png","targetRectangle":{"y":232.76564073562622,"x":1392.8702132304195,"width":346.35734462738037,"height":97.664727926254272}},{"text":"","targetRectangle":{"y":536.41095165615457,"x":889.99999950725226,"width":139.99999999999989,"height":49}},{"text":"home.png","targetRectangle":{"y":177.70155334472656,"x":358.30960083007812,"width":300,"height":187.29165649414062}},{"text":"","targetRectangle":{"y":851.3035874964977,"x":718.16255818691513,"width":480.00000000000011,"height":117.59999799728394}},{"text":"","targetRectangle":{"y":784.806380212524,"x":889.9999905714061,"width":140.00000000000011,"height":49}},{"text":"Sub-page","targetRectangle":{"y":524.52831373333197,"x":114.77256446794757,"width":120.03,"height":43}},{"text":"page-note.png","targetRectangle":{"y":727.0634765625,"x":358.30960083007812,"width":300,"height":266.22378540039062}},{"text":"Note-page","targetRectangle":{"y":838.67537794231635,"x":108.54756265596637,"width":132.47999999999999,"height":43}}],"baseLayer":{"animations":[],"initialState":{"affineTransform":[1,0,0,1,0,0],"masksToBounds":false,"rotation":0,"scale":1,"position":{"pointX":960,"pointY":540},"width":1920,"sublayerTransform":[1,0,0,0,0,1,0,0,0,0,1,0,0,0,0,1],"contentsRect":{"y":0,"x":0,"width":1,"height":1},"opacity":1,"edgeAntialiasingMask":251658240,"height":1080,"hidden":false,"anchorPoint":{"pointX":0.5,"pointY":0.5}},"objectID":"0","layers":[{"animations":[],"initialState":{"affineTransform":[1,0,0,1,0,0],"masksToBounds":false,"rotation":0,"scale":1,"position":{"pointX":960,"pointY":540},"width":1920,"sublayerTransform":[1,0,0,0,0,1,0,0,0,0,1,-0.00035007912466775983,0,0,0,1],"contentsRect":{"y":0,"x":0,"width":1,"height":1},"opacity":1,"edgeAntialiasingMask":251658240,"height":1080,"hidden":false,"anchorPoint":{"pointX":0.5,"pointY":0.5}},"layers":[{"animations":[],"initialState":{"affineTransform":[1,0,0,1,0,0],"masksToBounds":false,"rotation":0,"scale":1,"position":{"pointX":960,"pointY":540},"width":1920,"sublayerTransform":[1,0,0,0,0,1,0,0,0,0,1,0,0,0,0,1],"contentsRect":{"y":0,"x":0,"width":1,"height":1},"opacity":1,"edgeAntialiasingMask":251658240,"height":1080,"hidden":false,"anchorPoint":{"pointX":0.5,"pointY":0.5}},"layers":[{"animations":[],"layers":[],"texturedRectangle":{"isBackgroundTexture":true,"singleTextureOpacity":1,"textureType":1,"textBaseline":0,"textXHeight":0,"isVerticalText":false},"initialState":{"affineTransform":[1,0,0,1,0,0],"masksToBounds":false,"rotation":0,"scale":1,"position":{"pointX":960,"pointY":540},"width":1920,"sublayerTransform":[1,0,0,0,0,1,0,0,0,0,1,0,0,0,0,1],"contentsRect":{"y":0,"x":0,"width":1,"height":1},"opacity":1,"edgeAntialiasingMask":0,"height":1080,"hidden":false,"anchorPoint":{"pointX":0.5,"pointY":0.5}},"texture":"2833E5D319081570F97B4EAA52A46BB0"}]}]},{"animations":[],"initialState":{"affineTransform":[1,0,0,1,0,0],"masksToBounds":false,"rotation":0,"scale":1,"position":{"pointX":960.00000000000023,"pointY":117.89044952392581},"width":1728,"sublayerTransform":[1,0,0,0,0,1,0,0,0,0,1,0,0,0,0,1],"contentsRect":{"y":0,"x":0,"width":1,"height":1},"opacity":1,"edgeAntialiasingMask":251658240,"height":138.96035766601562,"hidden":false,"anchorPoint":{"pointX":0.5,"pointY":0.5}},"layers":[{"animations":[],"layers":[],"texturedRectangle":{"singleTextureOpacity":1,"textXHeight":0.56923076923076932,"textBaseline":0.94000930969531793,"isBackgroundTexture":true,"isVerticalText":false,"textColor":[0.39215686917304993,0.78431373834609985,0,1],"textureType":6},"initialState":{"affineTransform":[1,0,0,1,0,0],"masksToBounds":false,"rotation":0,"scale":1,"position":{"pointX":864,"pointY":69.480178833007812},"width":352,"sublayerTransform":[1,0,0,0,0,1,0,0,0,0,1,0,0,0,0,1],"contentsRect":{"y":0,"x":0,"width":1,"height":1},"opacity":1,"edgeAntialiasingMask":0,"height":39,"hidden":false,"anchorPoint":{"pointX":0.49715909090909155,"pointY":-0.28486026861728692}},"texture":"D6ACCEF746E29E97D128626FF2816D0F"}]},{"animations":[],"initialState":{"affineTransform":[1,0,0,1,0,0],"masksToBounds":false,"rotation":0,"scale":1,"position":{"pointX":960.00000000000023,"pointY":117.89044952392581},"width":1728,"sublayerTransform":[1,0,0,0,0,1,0,0,0,0,1,0,0,0,0,1],"contentsRect":{"y":0,"x":0,"width":1,"height":1},"opacity":1,"edgeAntialiasingMask":251658240,"height":138.96035766601562,"hidden":false,"anchorPoint":{"pointX":0.5,"pointY":0.5}},"layers":[{"animations":[],"layers":[],"texturedRectangle":{"singleTextureOpacity":1,"textXHeight":0.58823529411764708,"textBaseline":0.85118110273398662,"isBackgroundTexture":true,"isVerticalText":false,"textColor":[0.39215686917304993,0.78431373834609985,0,1],"textureType":6},"initialState":{"affineTransform":[1,0,0,1,0,0],"masksToBounds":false,"rotation":0,"scale":1,"position":{"pointX":864,"pointY":69.480178833007812},"width":248,"sublayerTransform":[1,0,0,0,0,1,0,0,0,0,1,0,0,0,0,1],"contentsRect":{"y":0,"x":0,"width":1,"height":1},"opacity":1,"edgeAntialiasingMask":0,"height":51,"hidden":false,"anchorPoint":{"pointX":0.50000000000000089,"pointY":1.0958911671358003}},"texture":"3B4F8D6EE81A914129782883B58270E9"}]},{"animations":[],"initialState":{"affineTransform":[1,0,0,1,0,0],"masksToBounds":false,"rotation":0,"scale":1,"position":{"pointX":199.78756504968891,"pointY":271.34736690639716},"width":250,"sublayerTransform":[1,0,0,0,0,1,0,0,0,0,1,0,0,0,0,1],"contentsRect":{"y":0,"x":0,"width":1,"height":1},"opacity":1,"edgeAntialiasingMask":251658240,"height":91.757492065429688,"hidden":false,"anchorPoint":{"pointX":0.5,"pointY":0.5}},"layers":[{"animations":[],"layers":[],"texturedRectangle":{"isBackgroundTexture":true,"singleTextureOpacity":1,"textureType":5,"textBaseline":0,"textXHeight":0,"isVerticalText":false},"initialState":{"affineTransform":[1,0,0,1,0,0],"masksToBounds":false,"rotation":0,"scale":1,"position":{"pointX":100,"pointY":45.878746032714844},"width":205,"sublayerTransform":[1,0,0,0,0,1,0,0,0,0,1,0,0,0,0,1],"contentsRect":{"y":0,"x":0,"width":1,"height":1},"opacity":1,"edgeAntialiasingMask":0,"height":97,"hidden":false,"anchorPoint":{"pointX":0.50140275633994591,"pointY":0.498426462952548}},"texture":"0E8FEB164291BE6990A485D710DD11FA"}]},{"animations":[],"initialState":{"affineTransform":[1,0,0,1,0,0],"masksToBounds":false,"rotation":0,"scale":1,"position":{"pointX":466.53158187866211,"pointY":271.34738159179688},"width":383.55603790283203,"sublayerTransform":[1,0,0,0,0,1,0,0,0,0,1,0,0,0,0,1],"contentsRect":{"y":0,"x":0,"width":1,"height":1},"opacity":1,"edgeAntialiasingMask":251658240,"height":187.29165649414062,"hidden":false,"anchorPoint":{"pointX":0.5,"pointY":0.5}},"layers":[{"animations":[],"layers":[],"texturedRectangle":{"isBackgroundTexture":true,"singleTextureOpacity":1,"textureType":5,"textBaseline":0,"textXHeight":0,"isVerticalText":false},"initialState":{"affineTransform":[1,0,0,1,0,0],"masksToBounds":false,"rotation":0,"scale":1,"position":{"pointX":191.77801895141602,"pointY":93.645828247070312},"width":387,"sublayerTransform":[1,0,0,0,0,1,0,0,0,0,1,0,0,0,0,1],"contentsRect":{"y":0,"x":0,"width":1,"height":1},"opacity":1,"edgeAntialiasingMask":0,"height":190,"hidden":false,"anchorPoint":{"pointX":0.50008160692160752,"pointY":0.50182832416735201}},"texture":"7D0D6ADCFF5A1DA84875F396A1F3D49A"}]},{"animations":[],"initialState":{"affineTransform":[1,0,0,1,0,0],"masksToBounds":false,"rotation":0,"scale":1,"position":{"pointX":199.78756504968891,"pointY":546.02833614467841},"width":250,"sublayerTransform":[1,0,0,0,0,1,0,0,0,0,1,0,0,0,0,1],"contentsRect":{"y":0,"x":0,"width":1,"height":1},"opacity":1,"edgeAntialiasingMask":251658240,"height":91.757492065429688,"hidden":false,"anchorPoint":{"pointX":0.5,"pointY":0.5}},"layers":[{"animations":[],"layers":[],"texturedRectangle":{"isBackgroundTexture":true,"singleTextureOpacity":1,"textureType":5,"textBaseline":0,"textXHeight":0,"isVerticalText":false},"initialState":{"affineTransform":[1,0,0,1,0,0],"masksToBounds":false,"rotation":0,"scale":1,"position":{"pointX":100,"pointY":45.878746032714844},"width":205,"sublayerTransform":[1,0,0,0,0,1,0,0,0,0,1,0,0,0,0,1],"contentsRect":{"y":0,"x":0,"width":1,"height":1},"opacity":1,"edgeAntialiasingMask":0,"height":96,"hidden":false,"anchorPoint":{"pointX":0.50140275633994591,"pointY":0.50029516817373343}},"texture":"2E7045BD920F3487C77D8EABFECE1D2D"}]},{"animations":[],"initialState":{"affineTransform":[1,0,0,1,0,0],"masksToBounds":false,"rotation":0,"scale":1,"position":{"pointX":466.5315825343132,"pointY":546.18106079101562},"width":383.55605447292328,"sublayerTransform":[1,0,0,0,0,1,0,0,0,0,1,0,0,0,0,1],"contentsRect":{"y":0,"x":0,"width":1,"height":1},"opacity":1,"edgeAntialiasingMask":251658240,"height":318.430419921875,"hidden":false,"anchorPoint":{"pointX":0.5,"pointY":0.5}},"layers":[{"animations":[],"layers":[],"texturedRectangle":{"isBackgroundTexture":true,"singleTextureOpacity":1,"textureType":5,"textBaseline":0,"textXHeight":0,"isVerticalText":false},"initialState":{"affineTransform":[1,0,0,1,0,0],"masksToBounds":false,"rotation":0,"scale":1,"position":{"pointX":191.77802723646164,"pointY":159.2152099609375},"width":387,"sublayerTransform":[1,0,0,0,0,1,0,0,0,0,1,0,0,0,0,1],"contentsRect":{"y":0,"x":0,"width":1,"height":1},"opacity":1,"edgeAntialiasingMask":0,"height":322,"hidden":false,"anchorPoint":{"pointX":0.50008160861579642,"pointY":0.50056230059321627}},"texture":"A8DB8D9536F81A2527E0B05BA8FCC94D"}]},{"animations":[],"initialState":{"affineTransform":[1,0,0,1,0,0],"masksToBounds":false,"rotation":0,"scale":1,"position":{"pointX":199.78756504968891,"pointY":860.17540035366278},"width":250,"sublayerTransform":[1,0,0,0,0,1,0,0,0,0,1,0,0,0,0,1],"contentsRect":{"y":0,"x":0,"width":1,"height":1},"opacity":1,"edgeAntialiasingMask":251658240,"height":91.757492065429688,"hidden":false,"anchorPoint":{"pointX":0.5,"pointY":0.5}},"layers":[{"animations":[],"layers":[],"texturedRectangle":{"isBackgroundTexture":true,"singleTextureOpacity":1,"textureType":5,"textBaseline":0,"textXHeight":0,"isVerticalText":false},"initialState":{"affineTransform":[1,0,0,1,0,0],"masksToBounds":false,"rotation":0,"scale":1,"position":{"pointX":100,"pointY":45.878746032714844},"width":205,"sublayerTransform":[1,0,0,0,0,1,0,0,0,0,1,0,0,0,0,1],"contentsRect":{"y":0,"x":0,"width":1,"height":1},"opacity":1,"edgeAntialiasingMask":0,"height":97,"hidden":false,"anchorPoint":{"pointX":0.50140275633994591,"pointY":0.49665361189343071}},"texture":"D1BCC90F4A817BAEF10B4EC9B04D169D"}]},{"animations":[],"initialState":{"affineTransform":[1,0,0,1,0,0],"masksToBounds":false,"rotation":0,"scale":1,"position":{"pointX":466.53157806396484,"pointY":860.51001739501953},"width":383.55604553222656,"sublayerTransform":[1,0,0,0,0,1,0,0,0,0,1,0,0,0,0,1],"contentsRect":{"y":0,"x":0,"width":1,"height":1},"opacity":1,"edgeAntialiasingMask":251658240,"height":266.89308166503906,"hidden":false,"anchorPoint":{"pointX":0.5,"pointY":0.5}},"layers":[{"animations":[],"layers":[],"texturedRectangle":{"isBackgroundTexture":true,"singleTextureOpacity":1,"textureType":5,"textBaseline":0,"textXHeight":0,"isVerticalText":false},"initialState":{"affineTransform":[1,0,0,1,0,0],"masksToBounds":false,"rotation":0,"scale":1,"position":{"pointX":191.77802276611328,"pointY":133.44654083251953},"width":387,"sublayerTransform":[1,0,0,0,0,1,0,0,0,0,1,0,0,0,0,1],"contentsRect":{"y":0,"x":0,"width":1,"height":1},"opacity":1,"edgeAntialiasingMask":0,"height":269,"hidden":false,"anchorPoint":{"pointX":0.50008159706450861,"pointY":0.50003723938668976}},"texture":"4A112B40B3884597F33BB6F30BFED3E9"}]},{"animations":[],"initialState":{"affineTransform":[1,0,0,1,0,0],"masksToBounds":false,"rotation":0,"scale":1,"position":{"pointX":1024.4200897220485,"pointY":231.34256431655558},"width":352.28836059570324,"sublayerTransform":[1,0,0,0,0,1,0,0,0,0,1,0,0,0,0,1],"contentsRect":{"y":0,"x":0,"width":1,"height":1},"opacity":1,"edgeAntialiasingMask":251658240,"height":376.15777587890625,"hidden":false,"anchorPoint":{"pointX":0.5,"pointY":0.5}},"layers":[{"animations":[],"layers":[],"texturedRectangle":{"isBackgroundTexture":true,"singleTextureOpacity":1,"textureType":5,"textBaseline":0,"textXHeight":0,"isVerticalText":false},"initialState":{"affineTransform":[1,0,0,1,0,0],"masksToBounds":false,"rotation":0,"scale":1,"position":{"pointX":111.72409057617176,"pointY":309.78208923339844},"width":528,"sublayerTransform":[1,0,0,0,0,1,0,0,0,0,1,0,0,0,0,1],"contentsRect":{"y":0,"x":0,"width":1,"height":1},"opacity":1,"edgeAntialiasingMask":0,"height":305,"hidden":false,"anchorPoint":{"pointX":0.50000000000069811,"pointY":0.49851070691967508}},"texture":"87C15DFF8EDFD93167001BD43D51C037"}]},{"animations":[],"initialState":{"affineTransform":[1,0,0,1,0,0],"masksToBounds":false,"rotation":0,"scale":1,"position":{"pointX":1024.420089705769,"pointY":546.4894425094642},"width":352.28836059570301,"sublayerTransform":[1,0,0,0,0,1,0,0,0,0,1,0,0,0,0,1],"contentsRect":{"y":0,"x":0,"width":1,"height":1},"opacity":1,"edgeAntialiasingMask":251658240,"height":376.15777587890625,"hidden":false,"anchorPoint":{"pointX":0.5,"pointY":0.5}},"layers":[{"animations":[],"layers":[],"texturedRectangle":{"isBackgroundTexture":true,"singleTextureOpacity":1,"textureType":5,"textBaseline":0,"textXHeight":0,"isVerticalText":false},"initialState":{"affineTransform":[1,0,0,1,0,0],"masksToBounds":false,"rotation":0,"scale":1,"position":{"pointX":111.72409057617188,"pointY":276.40636444091797},"width":528,"sublayerTransform":[1,0,0,0,0,1,0,0,0,0,1,0,0,0,0,1],"contentsRect":{"y":0,"x":0,"width":1,"height":1},"opacity":1,"edgeAntialiasingMask":0,"height":238,"hidden":false,"anchorPoint":{"pointX":0.49999999996986633,"pointY":0.49923075214676066}},"texture":"8D8076FC571C884B99B78997664A31AB"}]},{"animations":[],"initialState":{"affineTransform":[1,0,0,1,0,0],"masksToBounds":false,"rotation":0,"scale":1,"position":{"pointX":1571.0955551465038,"pointY":503.46470681265339},"width":618.810302734375,"sublayerTransform":[1,0,0,0,0,1,0,0,0,0,1,0,0,0,0,1],"contentsRect":{"y":0,"x":0,"width":1,"height":1},"opacity":1,"edgeAntialiasingMask":251658240,"height":191.83839416503906,"hidden":false,"anchorPoint":{"pointX":0.5,"pointY":0.5}},"layers":[{"animations":[],"layers":[],"texturedRectangle":{"isBackgroundTexture":true,"singleTextureOpacity":1,"textureType":5,"textBaseline":0,"textXHeight":0,"isVerticalText":false},"initialState":{"affineTransform":[1,0,0,1,0,0],"masksToBounds":false,"rotation":0,"scale":1,"position":{"pointX":309.4051513671875,"pointY":95.919197082519531},"width":624,"sublayerTransform":[1,0,0,0,0,1,0,0,0,0,1,0,0,0,0,1],"contentsRect":{"y":0,"x":0,"width":1,"height":1},"opacity":1,"edgeAntialiasingMask":0,"height":197,"hidden":false,"anchorPoint":{"pointX":0.50015313324760224,"pointY":0.49982084676473804}},"texture":"1796028C98209D0165F52AB38FB587DF"}]},{"animations":[],"initialState":{"affineTransform":[1,0,0,1,0,0],"masksToBounds":false,"rotation":0,"scale":1,"position":{"pointX":1571.0955551302245,"pointY":793.37098727918237},"width":618.810302734375,"sublayerTransform":[1,0,0,0,0,1,0,0,0,0,1,0,0,0,0,1],"contentsRect":{"y":0,"x":0,"width":1,"height":1},"opacity":1,"edgeAntialiasingMask":251658240,"height":264.22378540039062,"hidden":false,"anchorPoint":{"pointX":0.5,"pointY":0.5}},"layers":[{"animations":[],"layers":[],"texturedRectangle":{"isBackgroundTexture":true,"singleTextureOpacity":1,"textureType":5,"textBaseline":0,"textXHeight":0,"isVerticalText":false},"initialState":{"affineTransform":[1,0,0,1,0,0],"masksToBounds":false,"rotation":0,"scale":1,"position":{"pointX":309.4051513671875,"pointY":132.11189270019531},"width":624,"sublayerTransform":[1,0,0,0,0,1,0,0,0,0,1,0,0,0,0,1],"contentsRect":{"y":0,"x":0,"width":1,"height":1},"opacity":1,"edgeAntialiasingMask":0,"height":269,"hidden":false,"anchorPoint":{"pointX":0.50015313322151367,"pointY":0.49952039880736943}},"texture":"E3ADDBBFD8171082E38ADE95F01AB209"}]},{"animations":[],"initialState":{"affineTransform":[1,0,0,1,0,0],"masksToBounds":false,"rotation":0,"scale":1,"position":{"pointX":1570.0954939921382,"pointY":258.774498462677},"width":420.1453857421875,"sublayerTransform":[1,0,0,0,0,1,0,0,0,0,1,0,0,0,0,1],"contentsRect":{"y":0,"x":0,"width":1,"height":1},"opacity":1,"edgeAntialiasingMask":251658240,"height":173.79164123535156,"hidden":false,"anchorPoint":{"pointX":0.5,"pointY":0.5}},"layers":[{"animations":[],"layers":[],"texturedRectangle":{"isBackgroundTexture":true,"singleTextureOpacity":1,"textureType":5,"textBaseline":0,"textXHeight":0,"isVerticalText":false},"initialState":{"affineTransform":[1,0,0,1,0,0],"masksToBounds":false,"rotation":0,"scale":1,"position":{"pointX":210.07269287109375,"pointY":86.895820617675781},"width":425,"sublayerTransform":[1,0,0,0,0,1,0,0,0,0,1,0,0,0,0,1],"contentsRect":{"y":0,"x":0,"width":1,"height":1},"opacity":1,"edgeAntialiasingMask":0,"height":179,"hidden":false,"anchorPoint":{"pointX":0.49904822115797232,"pointY":0.50153351096467602}},"texture":"99B4D0FF28E2692CD0C57104DAC27CED"}]},{"animations":[],"initialState":{"affineTransform":[1,0,0,1,0,0],"masksToBounds":false,"rotation":0,"scale":1,"position":{"pointX":1024.4200807699231,"pointY":794.88487106583364},"width":352.28836059570324,"sublayerTransform":[1,0,0,0,0,1,0,0,0,0,1,0,0,0,0,1],"contentsRect":{"y":0,"x":0,"width":1,"height":1},"opacity":1,"edgeAntialiasingMask":251658240,"height":376.15777587890625,"hidden":false,"anchorPoint":{"pointX":0.5,"pointY":0.5}},"layers":[{"animations":[],"layers":[],"texturedRectangle":{"isBackgroundTexture":true,"singleTextureOpacity":1,"textureType":5,"textBaseline":0,"textXHeight":0,"isVerticalText":false},"initialState":{"affineTransform":[1,0,0,1,0,0],"masksToBounds":false,"rotation":0,"scale":1,"position":{"pointX":111.72409057617188,"pointY":276.40636444091797},"width":528,"sublayerTransform":[1,0,0,0,0,1,0,0,0,0,1,0,0,0,0,1],"contentsRect":{"y":0,"x":0,"width":1,"height":1},"opacity":1,"edgeAntialiasingMask":0,"height":238,"hidden":false,"anchorPoint":{"pointX":0.49999998304591525,"pointY":0.50089221666932138}},"texture":"B9AA89F1E301910A2B675E6B21148B58"}]},{"animations":[],"initialState":{"affineTransform":[1,0,0,1,0,0],"masksToBounds":false,"rotation":0,"scale":1,"position":{"pointX":517.71886877409565,"pointY":702.31017504539955},"width":866.2203369140625,"sublayerTransform":[1,0,0,0,0,1,0,0,0,0,1,0,0,0,0,1],"contentsRect":{"y":0,"x":0,"width":1,"height":1},"opacity":1,"edgeAntialiasingMask":251658240,"height":560.9205322265625,"hidden":false,"anchorPoint":{"pointX":0.5,"pointY":0.5}},"layers":[{"animations":[],"layers":[],"texturedRectangle":{"isBackgroundTexture":true,"singleTextureOpacity":1,"textureType":5,"textBaseline":0,"textXHeight":0,"isVerticalText":false},"initialState":{"affineTransform":[1,0,0,1,0,0],"masksToBounds":false,"rotation":0,"scale":1,"position":{"pointX":433.11016845703119,"pointY":280.46026611328131},"width":869,"sublayerTransform":[1,0,0,0,0,1,0,0,0,0,1,0,0,0,0,1],"contentsRect":{"y":0,"x":0,"width":1,"height":1},"opacity":1,"edgeAntialiasingMask":0,"height":564,"hidden":true,"anchorPoint":{"pointX":0.50025186280103062,"pointY":0.50054995575425454}},"texture":"92F080D6EFD25320C74C7DA152EDEF71"}]},{"animations":[],"initialState":{"affineTransform":[1,0,0,1,0,0],"masksToBounds":false,"rotation":0,"scale":1,"position":{"pointX":1401.8605545725923,"pointY":702.3101750438293},"width":866.21875000000011,"sublayerTransform":[1,0,0,0,0,1,0,0,0,0,1,0,0,0,0,1],"contentsRect":{"y":0,"x":0,"width":1,"height":1},"opacity":1,"edgeAntialiasingMask":251658240,"height":554.8125,"hidden":false,"anchorPoint":{"pointX":0.5,"pointY":0.5}},"layers":[{"animations":[],"layers":[],"texturedRectangle":{"isBackgroundTexture":true,"singleTextureOpacity":1,"textureType":5,"textBaseline":0,"textXHeight":0,"isVerticalText":false},"initialState":{"affineTransform":[1,0,0,1,0,0],"masksToBounds":false,"rotation":0,"scale":1,"position":{"pointX":433.10585728894887,"pointY":277.403215050028},"width":869,"sublayerTransform":[1,0,0,0,0,1,0,0,0,0,1,0,0,0,0,1],"contentsRect":{"y":0,"x":0,"width":1,"height":1},"opacity":1,"edgeAntialiasingMask":0,"height":558,"hidden":true,"anchorPoint":{"pointX":0.50041085944941432,"pointY":0.50055043027572987}},"texture":"78B2571B4C942879C0A8C8D665EEA93B"}]},{"animations":[],"initialState":{"affineTransform":[1,0,0,1,0,0],"masksToBounds":false,"rotation":0,"scale":1,"position":{"pointX":559.23453246605141,"pointY":280.77283516631735},"width":980.53576660156239,"sublayerTransform":[1,0,0,0,0,1,0,0,0,0,1,0,0,0,0,1],"contentsRect":{"y":0,"x":0,"width":1,"height":1},"opacity":1,"edgeAntialiasingMask":251658240,"height":134.3441172087874,"hidden":false,"anchorPoint":{"pointX":0.5,"pointY":0.5}},"layers":[{"animations":[],"layers":[],"texturedRectangle":{"singleTextureOpacity":1,"textXHeight":0,"shapePath":{"lineWidth":1,"flatness":0.59999999999999998,"lineCapStyle":0,"elements":[{"type":"MoveToPoint","points":[[452.76612967049175,1.6007765619236238]]},{"type":"AddLine","points":[[982.50241576683266,135.94489377071102]]},{"type":"AddLine","points":[[1.9666491652702689,135.94489377071102]]},{"type":"AddLine","points":[[452.76612967049175,1.6007765619236238]]},{"type":"CloseSubpath"},{"type":"MoveToPoint","points":[[452.76612967049175,1.6007765619236238]]}],"windingRule":0,"lineJoinStyle":0,"miterLimit":10},"isBackgroundTexture":true,"textBaseline":0,"isVerticalText":false,"textureType":5},"initialState":{"affineTransform":[1,0,0,1,0,0],"masksToBounds":false,"rotation":0,"scale":1,"position":{"pointX":490.26788330078114,"pointY":67.172058604393726},"width":984,"sublayerTransform":[1,0,0,0,0,1,0,0,0,0,1,0,0,0,0,1],"contentsRect":{"y":0,"x":0,"width":1,"height":1},"opacity":1,"edgeAntialiasingMask":0,"height":137,"hidden":true,"anchorPoint":{"pointX":0.50023834600208472,"pointY":0.50199149756436023}},"texture":"7F9169F746AA870A0DEF2212163E8B53"}]},{"animations":[],"initialState":{"affineTransform":[1,0,0,1,0,0],"masksToBounds":false,"rotation":0,"scale":1,"position":{"pointX":517.71886873992412,"pointY":384.89740137768382},"width":301.82842807842053,"sublayerTransform":[1,0,0,0,0,1,0,0,0,0,1,0,0,0,0,1],"contentsRect":{"y":0,"x":0,"width":1,"height":1},"opacity":1,"edgeAntialiasingMask":251658240,"height":45.82842784000195,"hidden":false,"anchorPoint":{"pointX":0.5,"pointY":0.5}},"layers":[{"animations":[],"layers":[],"texturedRectangle":{"singleTextureOpacity":1,"textXHeight":0,"shapePath":{"lineWidth":1,"flatness":0.59999999999999998,"lineCapStyle":0,"elements":[{"type":"MoveToPoint","points":[[3.2188682630869607,3.3974010200559519]]},{"type":"AddLine","points":[[302.21886921676128,3.3974010200559519]]},{"type":"AddLine","points":[[302.21886921676128,46.397401735311689]]},{"type":"AddLine","points":[[3.2188682630869607,46.397401735311689]]},{"type":"CloseSubpath"},{"type":"MoveToPoint","points":[[3.2188682630869607,3.3974010200559519]]}],"windingRule":0,"lineJoinStyle":0,"miterLimit":10},"isBackgroundTexture":true,"textBaseline":0,"isVerticalText":false,"textureType":5},"initialState":{"affineTransform":[1,0,0,1,0,0],"masksToBounds":false,"rotation":0,"scale":1,"position":{"pointX":150.91421356237311,"pointY":22.914213562373106},"width":305,"sublayerTransform":[1,0,0,0,0,1,0,0,0,0,1,0,0,0,0,1],"contentsRect":{"y":0,"x":0,"width":1,"height":1},"opacity":1,"edgeAntialiasingMask":0,"height":49,"hidden":true,"anchorPoint":{"pointX":0.50071760086258021,"pointY":0.50811022489910107}},"texture":"C01262779C34742FCAB4F9FA6FF78572"}]},{"animations":[],"initialState":{"affineTransform":[1,0,0,1,0,0],"masksToBounds":false,"rotation":0,"scale":1,"position":{"pointX":517.71886873992412,"pointY":384.89740137768382},"width":301.82842807842053,"sublayerTransform":[1,0,0,0,0,1,0,0,0,0,1,0,0,0,0,1],"contentsRect":{"y":0,"x":0,"width":1,"height":1},"opacity":1,"edgeAntialiasingMask":251658240,"height":45.82842784000195,"hidden":false,"anchorPoint":{"pointX":0.5,"pointY":0.5}},"layers":[{"animations":[],"layers":[],"texturedRectangle":{"singleTextureOpacity":1,"textXHeight":0.55384615384615388,"textBaseline":0.81682248012858871,"isBackgroundTexture":true,"isVerticalText":false,"textColor":[0.37036359310150146,0.37036353349685669,0.37036359310150146,1],"textureType":6},"initialState":{"affineTransform":[1,0,0,1,0,0],"masksToBounds":false,"rotation":0,"scale":1,"position":{"pointX":150.91421356237311,"pointY":22.914213562373106},"width":290,"sublayerTransform":[1,0,0,0,0,1,0,0,0,0,1,0,0,0,0,1],"contentsRect":{"y":0,"x":0,"width":1,"height":1},"opacity":1,"edgeAntialiasingMask":0,"height":26,"hidden":true,"anchorPoint":{"pointX":0.49903058021754126,"pointY":0.49605388538676737}},"texture":"9A6D3BC21262E5851D204FFA9173D32E"}]},{"animations":[],"initialState":{"affineTransform":[1,0,0,1,0,0],"masksToBounds":false,"rotation":0,"scale":1,"position":{"pointX":1401.860554575597,"pointY":391.55801176764993},"width":368.1644161231593,"sublayerTransform":[1,0,0,0,0,1,0,0,0,0,1,0,0,0,0,1],"contentsRect":{"y":0,"x":0,"width":1,"height":1},"opacity":1,"edgeAntialiasingMask":251658240,"height":48.028605151899228,"hidden":false,"anchorPoint":{"pointX":0.5,"pointY":0.5}},"layers":[{"animations":[],"layers":[],"texturedRectangle":{"singleTextureOpacity":1,"textXHeight":0,"shapePath":{"lineWidth":1,"flatness":0.59999999999999998,"lineCapStyle":0,"elements":[{"type":"MoveToPoint","points":[[3.192560076390464,2.9579227540734223]]},{"type":"AddLine","points":[[368.52854907480355,2.9579227540734223]]},{"type":"AddLine","points":[[368.52854907480355,48.158100781226437]]},{"type":"AddLine","points":[[3.192560076390464,48.158100781226437]]},{"type":"CloseSubpath"},{"type":"MoveToPoint","points":[[3.192560076390464,2.9579227540734223]]}],"windingRule":0,"lineJoinStyle":0,"miterLimit":10},"isBackgroundTexture":true,"textBaseline":0,"isVerticalText":false,"textureType":5},"initialState":{"affineTransform":[1,0,0,1,0,0],"masksToBounds":false,"rotation":0,"scale":1,"position":{"pointX":184.082213562373,"pointY":24.01430239713568},"width":371,"sublayerTransform":[1,0,0,0,0,1,0,0,0,0,1,0,0,0,0,1],"contentsRect":{"y":0,"x":0,"width":1,"height":1},"opacity":1,"edgeAntialiasingMask":0,"height":51,"hidden":true,"anchorPoint":{"pointX":0.50097186004417882,"pointY":0.50113748213403908}},"texture":"EDE3317141A20CA829F956C46062911A"}]},{"animations":[],"initialState":{"affineTransform":[1,0,0,1,0,0],"masksToBounds":false,"rotation":0,"scale":1,"position":{"pointX":1401.860554575597,"pointY":391.55801176764993},"width":368.1644161231593,"sublayerTransform":[1,0,0,0,0,1,0,0,0,0,1,0,0,0,0,1],"contentsRect":{"y":0,"x":0,"width":1,"height":1},"opacity":1,"edgeAntialiasingMask":251658240,"height":48.028605151899228,"hidden":false,"anchorPoint":{"pointX":0.5,"pointY":0.5}},"layers":[{"animations":[],"layers":[],"texturedRectangle":{"singleTextureOpacity":1,"textXHeight":0.55384615384615388,"textBaseline":0.84608014949561239,"isBackgroundTexture":true,"isVerticalText":false,"textColor":[0.37036359310150146,0.37036353349685669,0.37036359310150146,1],"textureType":6},"initialState":{"affineTransform":[1,0,0,1,0,0],"masksToBounds":false,"rotation":0,"scale":1,"position":{"pointX":184.082213562373,"pointY":24.01430239713568},"width":356,"sublayerTransform":[1,0,0,0,0,1,0,0,0,0,1,0,0,0,0,1],"contentsRect":{"y":0,"x":0,"width":1,"height":1},"opacity":1,"edgeAntialiasingMask":0,"height":26,"hidden":true,"anchorPoint":{"pointX":0.49960831482132123,"pointY":0.48300044572446138}},"texture":"DE7E69848A2A2C788BBBE86BB17CBA75"}]}]}}]}